Workbook

Sheet Supplier_Dashboard
A1: Zomorod Supplier Intelligence — Dashboard
A3: Total suppliers (with email) | B3: =COUNTIF(Supplier_Intelligence!$I$2:$I$3001,"*?@*.*")
A4: Total LOW risk | B4: =COUNTIF(Supplier_Intelligence!$R$2:$R$3001,"LOW")
A5: Total MED risk | B5: =COUNTIF(Supplier_Intelligence!$R$2:$R$3001,"MED")
A6: Total HIGH risk | B6: =COUNTIF(Supplier_Intelligence!$R$2:$R$3001,"HIGH")
A8: By Country (email-verified) | D8: By Category (email-verified)
A9: Country | B9: Suppliers | D9: Primary Category | E9: Suppliers
A10: Malaysia | B10: =COUNTIFS(Supplier_Intelligence!$C$2:$C$3001,A10,Supplier_Intelligence!$I$2:$I$3001,"*?@*.*") | D10: Wound Care | E10: =COUNTIFS(Supplier_Intelligence!$E$2:$E$3001,D10,Supplier_Intelligence!$I$2:$I$3001,"*?@*.*")
A11: Turkey | B11: =COUNTIFS(Supplier_Intelligence!$C$2:$C$3001,A11,Supplier_Intelligence!$I$2:$I$3001,"*?@*.*") | D11: Syringes & Needles | E11: =COUNTIFS(Supplier_Intelligence!$E$2:$E$3001,D11,Supplier_Intelligence!$I$2:$I$3001,"*?@*.*")
A12: China | B12: =COUNTIFS(Supplier_Intelligence!$C$2:$C$3001,A12,Supplier_Intelligence!$I$2:$I$3001,"*?@*.*") | D12: IV Cannulas | E12: =COUNTIFS(Supplier_Intelligence!$E$2:$E$3001,D12,Supplier_Intelligence!$I$2:$I$3001,"*?@*.*")
A13: Egypt | B13: =COUNTIFS(Supplier_Intelligence!$C$2:$C$3001,A13,Supplier_Intelligence!$I$2:$I$3001,"*?@*.*") | D13: IV Infusion Sets | E13: =COUNTIFS(Supplier_Intelligence!$E$2:$E$3001,D13,Supplier_Intelligence!$I$2:$I$3001,"*?@*.*")
A14: Germany | B14: =COUNTIFS(Supplier_Intelligence!$C$2:$C$3001,A14,Supplier_Intelligence!$I$2:$I$3001,"*?@*.*") | D14: Catheters | E14: =COUNTIFS(Supplier_Intelligence!$E$2:$E$3001,D14,Supplier_Intelligence!$I$2:$I$3001,"*?@*.*")
A15: France | B15: =COUNTIFS(Supplier_Intelligence!$C$2:$C$3001,A15,Supplier_Intelligence!$I$2:$I$3001,"*?@*.*") | D15: Gloves | E15: =COUNTIFS(Supplier_Intelligence!$E$2:$E$3001,D15,Supplier_Intelligence!$I$2:$I$3001,"*?@*.*")
A16: Italy | B16: =COUNTIFS(Supplier_Intelligence!$C$2:$C$3001,A16,Supplier_Intelligence!$I$2:$I$3001,"*?@*.*") | D16: PPE | E16: =COUNTIFS(Supplier_Intelligence!$E$2:$E$3001,D16,Supplier_Intelligence!$I$2:$I$3001,"*?@*.*")
A17: Spain | B17: =COUNTIFS(Supplier_Intelligence!$C$2:$C$3001,A17,Supplier_Intelligence!$I$2:$I$3001,"*?@*.*") | D17: Gauze & Bandages | E17: =COUNTIFS(Supplier_Intelligence!$E$2:$E$3001,D17,Supplier_Intelligence!$I$2:$I$3001,"*?@*.*")
A18: United Kingdom | B18: =COUNTIFS(Supplier_Intelligence!$C$2:$C$3001,A18,Supplier_Intelligence!$I$2:$I$3001,"*?@*.*") | D18: Disinfectants | E18: =COUNTIFS(Supplier_Intelligence!$E$2:$E$3001,D18,Supplier_Intelligence!$I$2:$I$3001,"*?@*.*")
D19: Lab Consumables | E19: =COUNTIFS(Supplier_Intelligence!$E$2:$E$3001,D19,Supplier_Intelligence!$I$2:$I$3001,"*?@*.*")

Sheet RFQ_Batch_Generator
A1: RFQ Batch Generator (LOW/MED recommended)
J2: Categories | K2: Countries | L2: RiskLevels
A3: Primary Category (optional) | J3: Wound Care | K3: Malaysia | L3: LOW
A4: Country (optional) | J4: Syringes & Needles | K4: Turkey | L4: MED
A5: Max Risk Level | B5: MED | J5: IV Cannulas | K5: China | L5: HIGH
A6: Batch Size | B6: 100 | J6: IV Infusion Sets | K6: Egypt
A7: Batch # | B7: 1 | J7: Catheters | K7: Germany
J8: Gloves | K8: France
A9: Company | B9: Email(s) | C9: Country | D9: Primary_Category | E9: Risk_Level | F9: Evidence_URL | J9: PPE | K9: Italy
A10: =LET(cat,$B$3,cty,$B$4,maxRisk,$B$5,batchSize,$B$6,batchNum,$B$7,tbl,Supplier_Intelligence!$A$2:$U$3001,co,INDEX(tbl,,2),em,INDEX(tbl,,9),country,INDEX(tbl,,3),pcat,INDEX(tbl,,5),risk,INDEX(tbl,,18),ev,INDEX(tbl,,15),isRisk,IF(maxRisk="LOW",risk="LOW",IF(maxRisk="MED",(risk="LOW")+(risk="MED"),1)),isCat,IF(cat="",1,pcat=cat),isCty,IF(cty="",1,country=cty),mask,(co<>"")*(em<>"")*isRisk*isCat*isCty,filtered,FILTER(HSTACK(co,em,country,pcat,risk,ev),mask,""),start,(batchNum-1)*batchSize+1,TAKE(DROP(filtered,start-1),batchSize)) | J10: Gauze & Bandages | K10: Spain
J11: Disinfectants | K11: United Kingdom
J12: Lab Consumables

Sheet README
A1: Zomorod Supplier Intelligence — AutoFill Workbook (180 suppliers)
A2: Purpose | B2: Collect 180 verified manufacturers + exporters with emails, mapped to Zomorod categories, with evidence links and risk scoring.
A3: How it works | B3: Run the scraper in Codespaces to auto-fill 'Supplier_Intelligence'. Fix A: use multi-source crawling + Seed_URLs. Fix B: increase Max_Pages/Max_Items in Source_Config.
A4: Categories | B4: Wound Care; Syringes & Needles; IV Cannulas; IV Infusion Sets; Catheters; Gloves; PPE; Gauze & Bandages; Disinfectants; Lab Consumables
A6: Minimum acceptance rule | B6: Rows must have: Company + Email(s) + Country + Primary_Category + Evidence_URL.

Sheet Supplier_Intelligence
A1: Supplier_ID | B1: Company | C1: Country | D1: Supplier_Type | E1: Primary_Category | F1: Secondary_Categories | G1: Product_Focus (free text) | H1: Website | I1: Email(s) | J1: Phone/WhatsApp | K1: Export_Experience (explicit) | L1: Cert_ISO13485_Claim | M1: Cert_CE_Claim | N1: Cert_Other (FDA/UKCA/etc.) | O1: Evidence_URL (email or cert claim page) | P1: Expected_Price_Range_USD (sanity check) | Q1: Risk_Score (0=low,100=high) | R1: Risk_Level | S1: Status | T1: Last_Checked | U1: Notes
A2: 1 | B2: MAX Meditech Pvt. Ltd. - Leading Manufacturer of High-Quality Medical Devices for Mechanical Ventilation | D2: Manufacturer | E2: PPE | F2: Wound Care, Lab Consumables, Syringes & Needles, IV Infusion Sets, Gauze & Bandages, Disinfectants, IV Cannulas, Catheters | H2: https://www.medzell.net/main-categories-application/therapeutic-devices/ | I2: jithu.t@maxventilator.com | L2: Stated | N2: TUV | O2: https://www.medzell.net/company/a-b-industries/ | Q2: 10 | R2: =IF(Q2="","",IF(Q2>=60,"HIGH",IF(Q2>=30,"MEDIUM","LOW"))) | S2: New | T2: 2026-03-05 | U2: Seed=Medzell; Seed-file: output/medzell_company_urls.txt
A3: 2 | B3: Aadhar Medicare: Innovative Knee Supports, Body Belts, and Medical Devices | D3: Manufacturer | E3: PPE | F3: Wound Care, Gauze & Bandages, Lab Consumables, Syringes & Needles, IV Infusion Sets, Disinfectants, IV Cannulas, Catheters | H3: https://www.medzell.net/main-categories-application/therapeutic-devices/ | I3: sales@aadharmedicare.com | N3: TUV | O3: https://www.medzell.net/company/aadhar-medicare-private-limited/ | Q3: 25 | R3: =IF(Q3="","",IF(Q3>=60,"HIGH",IF(Q3>=30,"MEDIUM","LOW"))) | S3: New | T3: 2026-03-05 | U3: Seed=Medzell; Seed-file: output/medzell_company_urls.txt
A4: 3 | B4: aap Implantate AG | Leading Global Medical Technology for Trauma Care | D4: Manufacturer | E4: PPE | F4: Wound Care, Lab Consumables, Syringes & Needles, IV Infusion Sets, Gauze & Bandages, Disinfectants, IV Cannulas, Catheters | H4: https://www.medzell.net/main-categories-application/therapeutic-devices/ | I4: r.behrens@aap.de | N4: FDA, TUV | O4: https://www.medzell.net/company/aap-implantate-ag/ | Q4: 25 | R4: =IF(Q4="","",IF(Q4>=60,"HIGH",IF(Q4>=30,"MEDIUM","LOW"))) | S4: New | T4: 2026-03-05 | U4: Seed=Medzell; Seed-file: output/medzell_company_urls.txt
A5: 4 | B5: Revolutionary Post-Mastectomy Care Solutions | Aarna Biomedical Products Private Limited | D5: Manufacturer | E5: PPE | F5: Wound Care, Lab Consumables, Syringes & Needles, IV Infusion Sets, Gauze & Bandages, Disinfectants, IV Cannulas, Catheters | H5: https://www.medzell.net/main-categories-application/therapeutic-devices/ | I5: pawan.paterson@gmail.com | L5: Stated | N5: TUV | O5: https://www.medzell.net/company/aarna-biomedical-products-private-limited/ | Q5: 30 | R5: =IF(Q5="","",IF(Q5>=60,"HIGH",IF(Q5>=30,"MEDIUM","LOW"))) | S5: New | T5: 2026-03-05 | U5: Seed=Medzell; Seed-file: output/medzell_company_urls.txt
A6: 5 | B6: Accurex Biomedical Pvt. Ltd. - Leading Manufacturer of High-Quality Medical Diagnostic Solutions | D6: Manufacturer | E6: PPE | F6: Wound Care, Lab Consumables, Syringes & Needles, IV Infusion Sets, Gauze & Bandages, Disinfectants, IV Cannulas, Catheters | H6: https://www.medzell.net/main-categories-application/therapeutic-devices/ | I6: online1@accurex.net | N6: TUV | O6: https://www.medzell.net/company/accurex-biomedical-pvt-ltd/ | Q6: 25 | R6: =IF(Q6="","",IF(Q6>=60,"HIGH",IF(Q6>=30,"MEDIUM","LOW"))) | S6: New | T6: 2026-03-05 | U6: Seed=Medzell; Seed-file: output/medzell_company_urls.txt
A7: 6 | B7: Ace Cathtech – Indian Manufacturer of Catheterization, Nephrology & Critical Care Devices | D7: Manufacturer | E7: PPE | F7: Wound Care, Lab Consumables, Syringes & Needles, IV Infusion Sets, Gauze & Bandages, Disinfectants, IV Cannulas, Catheters | H7: https://www.medzell.net/main-categories-application/therapeutic-devices/ | I7: puneet.dohan1001@gmail.com | L7: Stated | N7: FDA, TUV | O7: https://www.medzell.net/company/ace-cathtech-pvt-ltd/ | Q7: 30 | R7: =IF(Q7="","",IF(Q7>=60,"HIGH",IF(Q7>=30,"MEDIUM","LOW"))) | S7: New | T7: 2026-03-05 | U7: Seed=Medzell; Seed-file: output/medzell_company_urls.txt
A8: 7 | B8: High-Quality Surgical Disposables, Hospital/Pharma Disposable Wear, and Cosmetic Products - Acuron Products | D8: Manufacturer | E8: PPE | F8: Wound Care, Lab Consumables, Syringes & Needles, IV Infusion Sets, Gauze & Bandages, Disinfectants, IV Cannulas, Catheters | H8: https://www.medzell.net/main-categories-application/therapeutic-devices/ | I8: acuronmarketing@gmail.com | N8: TUV | O8: https://www.medzell.net/company/acuron-products/ | Q8: 45 | R8: =IF(Q8="","",IF(Q8>=60,"HIGH",IF(Q8>=30,"MEDIUM","LOW"))) | S8: New | T8: 2026-03-05 | U8: Seed=Medzell; Seed-file: output/medzell_company_urls.txt
A9: 8 | B9: Adonis Medical Systems: Quality Imaging Solutions | D9: Manufacturer | E9: PPE | F9: Wound Care, Lab Consumables, Syringes & Needles, IV Infusion Sets, Gauze & Bandages, Disinfectants, IV Cannulas, Catheters | H9: https://www.medzell.net/main-categories-application/therapeutic-devices/ | I9: support@adonismedical.com | L9: Stated | N9: TUV | O9: https://www.medzell.net/company/adonis-medical-systems-private-limited/ | Q9: 10 | R9: =IF(Q9="","",IF(Q9>=60,"HIGH",IF(Q9>=30,"MEDIUM","LOW"))) | S9: New | T9: 2026-03-05 | U9: Seed=Medzell; Seed-file: output/medzell_company_urls.txt
A10: 9 | B10: Adva Medical: Innovative Surgical Products for Healthcare Professionals | D10: Manufacturer | E10: PPE | F10: Wound Care, Lab Consumables, Syringes & Needles, IV Infusion Sets, Gauze & Bandages, Disinfectants, IV Cannulas, Catheters | H10: https://www.medzell.net/main-categories-application/therapeutic-devices/ | I10: nazish.advamedical@gmail.com | L10: Stated | M10: Stated | N10: GMP, TUV | O10: https://www.medzell.net/company/adva-medical-india-pvt-ltd/ | Q10: 20 | R10: =IF(Q10="","",IF(Q10>=60,"HIGH",IF(Q10>=30,"MEDIUM","LOW"))) | S10: New | T10: 2026-03-05 | U10: Seed=Medzell; Seed-file: output/medzell_company_urls.txt
A11: 10 | B11: Premier Manufacturer and Global Supplier of NICU Equipment in India - Advance Mediplus Pvt. Ltd. | D11: Manufacturer | E11: PPE | F11: Wound Care, Lab Consumables, Syringes & Needles, IV Infusion Sets, Gauze & Bandages, Disinfectants, IV Cannulas, Catheters | H11: https://www.medzell.net/main-categories-application/therapeutic-devices/ | I11: contact@advancemedi.com | L11: Stated | N11: TUV | O11: https://www.medzell.net/company/advance-mediplus-pvt-ltd/ | Q11: 10 | R11: =IF(Q11="","",IF(Q11>=60,"HIGH",IF(Q11>=30,"MEDIUM","LOW"))) | S11: New | T11: 2026-03-05 | U11: Seed=Medzell; Seed-file: output/medzell_company_urls.txt
A12: 11 | B12: Discover Advanced LifeSciences Pvt. Ltd.: Pioneering B2B Manufacturer Bringing New Medical Technologies to the Indian Market | D12: Manufacturer | E12: PPE | F12: Wound Care, Lab Consumables, Syringes & Needles, IV Infusion Sets, Gauze & Bandages, Disinfectants, IV Cannulas, Catheters | H12: https://www.medzell.net/main-categories-application/therapeutic-devices/ | I12: sales@alspl.com | L12: Stated | M12: Stated | N12: TUV | O12: https://www.medzell.net/company/advanced-lifesciences-pvt-ltd/ | Q12: 0 | R12: =IF(Q12="","",IF(Q12>=60,"HIGH",IF(Q12>=30,"MEDIUM","LOW"))) | S12: New | T12: 2026-03-05 | U12: Seed=Medzell; Seed-file: output/medzell_company_urls.txt
A13: 12 | B13: Leading Global Manufacturer of Affordable and Accessible Medical Devices - Advanced MedTech Solutions Pvt. Ltd. | D13: Manufacturer | E13: PPE | F13: Wound Care, Lab Consumables, Syringes & Needles, IV Infusion Sets, Gauze & Bandages, Disinfectants, IV Cannulas, Catheters | H13: https://www.medzell.net/main-categories-application/therapeutic-devices/ | I13: shreenivass@amsltd.com | L13: Stated | N13: FDA, TUV | O13: https://www.medzell.net/company/advanced-medtech-solutions-pvt-ltd/ | Q13: 10 | R13: =IF(Q13="","",IF(Q13>=60,"HIGH",IF(Q13>=30,"MEDIUM","LOW"))) | S13: New | T13: 2026-03-05 | U13: Seed=Medzell; Seed-file: output/medzell_company_urls.txt
A14: 13 | B14: Advin Health Care – Global Manufacturer of Urology, Laparoscopy, Gynecology, Nephrology, Cardiology & Gastrology Devices | D14: Manufacturer | E14: PPE | F14: Wound Care, Lab Consumables, Syringes & Needles, IV Infusion Sets, Catheters, Gauze & Bandages, Disinfectants, IV Cannulas | H14: https://www.medzell.net/main-categories-application/therapeutic-devices/ | I14: advinhealthcare@gmail.com | L14: Stated | N14: TUV | O14: https://www.medzell.net/company/advin-health-care/ | Q14: 30 | R14: =IF(Q14="","",IF(Q14>=60,"HIGH",IF(Q14>=30,"MEDIUM","LOW"))) | S14: New | T14: 2026-03-05 | U14: Seed=Medzell; Seed-file: output/medzell_company_urls.txt
A15: 14 | B15: Aegis Lifesciences – Global Leader in Haemostatic & Surgical Medical Devices | D15: Manufacturer | E15: PPE | F15: Wound Care, Lab Consumables, Syringes & Needles, IV Infusion Sets, Gauze & Bandages, Disinfectants, IV Cannulas, Catheters | H15: https://www.medzell.net/main-categories-application/therapeutic-devices/ | I15: marketing.d@aegis-lifesciences.com | L15: Stated | M15: Stated | N15: FDA, GMP, TUV | O15: https://www.medzell.net/company/aegis-lifesciences-pvt-ltd/ | Q15: 0 | R15: =IF(Q15="","",IF(Q15>=60,"HIGH",IF(Q15>=30,"MEDIUM","LOW"))) | S15: New | T15: 2026-03-05 | U15: Seed=Medzell; Seed-file: output/medzell_company_urls.txt
A16: 15 | B16: Aether Biomedical | Advancing Bionic Prosthetics with Cutting-Edge Technology | D16: Manufacturer | E16: PPE | F16: Wound Care, Lab Consumables, Syringes & Needles, IV Infusion Sets, Gauze & Bandages, Disinfectants, IV Cannulas, Catheters | H16: https://www.medzell.net/main-categories-application/therapeutic-devices/ | I16: faith@aetherbiomedical.com | L16: Stated | N16: FDA, TUV | O16: https://www.medzell.net/company/aether-biomedical-sp-zo-o-prosthetics/ | Q16: 10 | R16: =IF(Q16="","",IF(Q16>=60,"HIGH",IF(Q16>=30,"MEDIUM","LOW"))) | S16: New | T16: 2026-03-05 | U16: Seed=Medzell; Seed-file: output/medzell_company_urls.txt
A17: 16 | B17: Affigenix Biosolutions Pvt. Ltd.: Tailored Biosolutions for Life Science and Diagnostics Sectors in India | D17: Manufacturer | E17: PPE | F17: Wound Care, Lab Consumables, Syringes & Needles, IV Infusion Sets, Gauze & Bandages, Disinfectants, IV Cannulas, Catheters | H17: https://www.medzell.net/main-categories-application/therapeutic-devices/ | I17: sales@affigenix.com | L17: Stated | N17: TUV | O17: https://www.medzell.net/company/affigenix-biosolutions-private-limited/ | Q17: 10 | R17: =IF(Q17="","",IF(Q17>=60,"HIGH",IF(Q17>=30,"MEDIUM","LOW"))) | S17: New | T17: 2026-03-05 | U17: Seed=Medzell; Seed-file: output/medzell_company_urls.txt
A18: 17 | B18: Agappe Diagnostics: Global Leader in In-Vitro Diagnostics | ISO Certified Manufacturer | D18: Manufacturer | E18: PPE | F18: Wound Care, Lab Consumables, Syringes & Needles, IV Infusion Sets, Gauze & Bandages, Disinfectants, IV Cannulas, Catheters | H18: https://www.medzell.net/main-categories-application/therapeutic-devices/ | I18: sreevisakh.kl@agappe.in | L18: Stated | N18: FDA, GMP, TUV | O18: https://www.medzell.net/company/agappe-diagnostics-limited/ | Q18: 10 | R18: =IF(Q18="","",IF(Q18>=60,"HIGH",IF(Q18>=30,"MEDIUM","LOW"))) | S18: New | T18: 2026-03-05 | U18: Seed=Medzell; Seed-file: output/medzell_company_urls.txt
A19: 18 | B19: AGD Biomedicals Pvt Ltd: Leading Manufacturer of Laboratory and IVD Equipment | D19: Manufacturer | E19: PPE | F19: Wound Care, Lab Consumables, Syringes & Needles, IV Infusion Sets, Gauze & Bandages, Disinfectants, IV Cannulas, Catheters | H19: https://www.medzell.net/main-categories-application/therapeutic-devices/ | I19: prabhat.sk77@gmail.com | L19: Stated | N19: TUV | O19: https://www.medzell.net/company/agd-biomedicals-pvt-ltd/ | Q19: 30 | R19: =IF(Q19="","",IF(Q19>=60,"HIGH",IF(Q19>=30,"MEDIUM","LOW"))) | S19: New | T19: 2026-03-05 | U19: Seed=Medzell; Seed-file: output/medzell_company_urls.txt
A20: 19 | B20: AI-OPTIC | Innovating Vision Screening with AI-Powered Technology | D20: Manufacturer | E20: PPE | F20: Wound Care, Lab Consumables, Syringes & Needles, IV Infusion Sets, Gauze & Bandages, Disinfectants, IV Cannulas, Catheters | H20: https://www.medzell.net/main-categories-application/therapeutic-devices/ | I20: helen@ai-optic.com | L20: Stated | N20: FDA, TUV | O20: https://www.medzell.net/company/ai-optic/ | Q20: 10 | R20: =IF(Q20="","",IF(Q20>=60,"HIGH",IF(Q20>=30,"MEDIUM","LOW"))) | S20: New | T20: 2026-03-05 | U20: Seed=Medzell; Seed-file: output/medzell_company_urls.txt
A21: 20 | B21: Aidlab - Empowering Remote Health, Fitness, and Science with Advanced Wearables | D21: Manufacturer | E21: PPE | F21: Wound Care, Lab Consumables, Syringes & Needles, IV Infusion Sets, Gauze & Bandages, Disinfectants, IV Cannulas, Catheters | H21: https://www.medzell.net/main-categories-application/therapeutic-devices/ | I21: jdomaszewicz@aidlab.com | L21: Stated | N21: TUV | O21: https://www.medzell.net/company/aidlab-inc/ | Q21: 10 | R21: =IF(Q21="","",IF(Q21>=60,"HIGH",IF(Q21>=30,"MEDIUM","LOW"))) | S21: New | T21: 2026-03-05 | U21: Seed=Medzell; Seed-file: output/medzell_company_urls.txt
A22: 21 | B22: Airgases Projects – Trusted Partner in Medical & Industrial Gas Solutions | D22: Manufacturer | E22: PPE | F22: Wound Care, Lab Consumables, Syringes & Needles, IV Infusion Sets, Gauze & Bandages, Disinfectants, IV Cannulas, Catheters | H22: https://www.medzell.net/main-categories-application/therapeutic-devices/ | I22: benganinamrata@gmail.com | L22: Stated | N22: TUV | O22: https://www.medzell.net/company/airgases-projects-pvt-ltd/ | Q22: 30 | R22: =IF(Q22="","",IF(Q22>=60,"HIGH",IF(Q22>=30,"MEDIUM","LOW"))) | S22: New | T22: 2026-03-05 | U22: Seed=Medzell; Seed-file: output/medzell_company_urls.txt
A23: 22 | B23: Airox Technologies: Pioneers and Leaders in PSA Oxygen Generation | D23: Manufacturer | E23: PPE | F23: Wound Care, Lab Consumables, Syringes & Needles, IV Infusion Sets, Gauze & Bandages, Disinfectants, IV Cannulas, Catheters | H23: https://www.medzell.net/main-categories-application/therapeutic-devices/ | I23: sales@airoxtechnologies.com | N23: TUV | O23: https://www.medzell.net/company/airox-technologies-limited/ | Q23: 25 | R23: =IF(Q23="","",IF(Q23>=60,"HIGH",IF(Q23>=30,"MEDIUM","LOW"))) | S23: New | T23: 2026-03-05 | U23: Seed=Medzell; Seed-file: output/medzell_company_urls.txt
A24: 23 | B24: Leading Manufacturer & Exporter of Hospital Consumables - Airways Surgical Pvt. Ltd. | D24: Manufacturer | E24: PPE | F24: Wound Care, Lab Consumables, Syringes & Needles, IV Infusion Sets, Gauze & Bandages, Disinfectants, IV Cannulas, Catheters | H24: https://www.medzell.net/main-categories-application/therapeutic-devices/ | I24: info@airwayssurgical.com | L24: Stated | N24: TUV | O24: https://www.medzell.net/company/airways-surgical-pvt-ltd/ | Q24: 10 | R24: =IF(Q24="","",IF(Q24>=60,"HIGH",IF(Q24>=30,"MEDIUM","LOW"))) | S24: New | T24: 2026-03-05 | U24: Seed=Medzell; Seed-file: output/medzell_company_urls.txt
A25: 24 | B25: AKAS Infusions: Trusted Manufacturer of High-Quality Drug Delivery Systems | D25: Manufacturer | E25: PPE | F25: Wound Care, Lab Consumables, Syringes & Needles, IV Infusion Sets, Gauze & Bandages, Disinfectants, IV Cannulas, Catheters | H25: https://www.medzell.net/main-categories-application/therapeutic-devices/ | I25: girish@akasinfusions.com | L25: Stated | M25: Stated | N25: TUV | O25: https://www.medzell.net/company/akas-infusions/ | Q25: 0 | R25: =IF(Q25="","",IF(Q25>=60,"HIGH",IF(Q25>=30,"MEDIUM","LOW"))) | S25: New | T25: 2026-03-05 | U25: Seed=Medzell; Seed-file: output/medzell_company_urls.txt
A26: 25 | B26: AKAS Technologies: Leading Manufacturer of Cutting-Edge Ophthalmology Products and Solutions | D26: Manufacturer | E26: PPE | F26: Wound Care, Lab Consumables, Syringes & Needles, IV Infusion Sets, Gauze & Bandages, Disinfectants, IV Cannulas, Catheters | H26: https://www.medzell.net/main-categories-application/therapeutic-devices/ | I26: exportakastech@gmail.com | L26: Stated | N26: TUV | O26: https://www.medzell.net/company/akas-technologies/ | Q26: 30 | R26: =IF(Q26="","",IF(Q26>=60,"HIGH",IF(Q26>=30,"MEDIUM","LOW"))) | S26: New | T26: 2026-03-05 | U26: Seed=Medzell; Seed-file: output/medzell_company_urls.txt
A27: 26 | B27: Akriti – Innovating Affordable Eye Care Solutions & Ophthalmic Implants | D27: Manufacturer | E27: PPE | F27: Wound Care, Lab Consumables, Syringes & Needles, IV Infusion Sets, Gauze & Bandages, Disinfectants, IV Cannulas, Catheters | H27: https://www.medzell.net/main-categories-application/therapeutic-devices/ | I27: sales.akriti@gmail.com | N27: TUV | O27: https://www.medzell.net/company/akriti-ophthalmic-pvt-ltd/ | Q27: 45 | R27: =IF(Q27="","",IF(Q27>=60,"HIGH",IF(Q27>=30,"MEDIUM","LOW"))) | S27: New | T27: 2026-03-05 | U27: Seed=Medzell; Seed-file: output/medzell_company_urls.txt
A28: 27 | B28: Quality, Reliability, and Innovation: A Deep Dive into Alan Electronic Systems Pvt. Ltd., Featuring CO2 Insufflators and ESUs. | D28: Manufacturer | E28: PPE | F28: Wound Care, Lab Consumables, Syringes & Needles, IV Infusion Sets, Gauze & Bandages, Disinfectants, IV Cannulas, Catheters | H28: https://www.medzell.net/main-categories-application/therapeutic-devices/ | I28: export@alanindia.net | L28: Stated | N28: TUV | O28: https://www.medzell.net/company/alan-electronics-systems-pvt-ltd/ | Q28: 10 | R28: =IF(Q28="","",IF(Q28>=60,"HIGH",IF(Q28>=30,"MEDIUM","LOW"))) | S28: New | T28: 2026-03-05 | U28: Seed=Medzell; Seed-file: output/medzell_company_urls.txt
A29: 28 | B29: Top-Quality Medical Imaging Solutions by Allans Medical Systems Pvt. Ltd. | D29: Manufacturer | E29: PPE | F29: Wound Care, Lab Consumables, Syringes & Needles, IV Infusion Sets, Gauze & Bandages, Disinfectants, IV Cannulas, Catheters | H29: https://www.medzell.net/main-categories-application/therapeutic-devices/ | I29: allansmedisys@gmail.com | N29: TUV | O29: https://www.medzell.net/company/allans-medical-systems-pvt-ltd/ | Q29: 45 | R29: =IF(Q29="","",IF(Q29>=60,"HIGH",IF(Q29>=30,"MEDIUM","LOW"))) | S29: New | T29: 2026-03-05 | U29: Seed=Medzell; Seed-file: output/medzell_company_urls.txt
A30: 29 | B30: Allengers Medical Systems Ltd. | India’s Premier Diagnostic Equipment Manufacturer | D30: Manufacturer | E30: PPE | F30: Wound Care, Lab Consumables, Syringes & Needles, IV Infusion Sets, Catheters, Gauze & Bandages, Disinfectants, IV Cannulas | H30: https://www.medzell.net/main-categories-application/therapeutic-devices/ | I30: online.marketing@allengers.net | L30: Stated | N30: FDA, TUV | O30: https://www.medzell.net/company/allengers-medical-systems-ltd/ | Q30: 10 | R30: =IF(Q30="","",IF(Q30>=60,"HIGH",IF(Q30>=30,"MEDIUM","LOW"))) | S30: New | T30: 2026-03-05 | U30: Seed=Medzell; Seed-file: output/medzell_company_urls.txt
A31: 30 | B31: Alliance Elemech – Trusted Manufacturer of Medical & Industrial Sterilization Equipment | D31: Manufacturer | E31: PPE | F31: Wound Care, Lab Consumables, Syringes & Needles, IV Infusion Sets, Gauze & Bandages, Disinfectants, IV Cannulas, Catheters | H31: https://www.medzell.net/main-categories-application/therapeutic-devices/ | I31: alliance.elemech@gmail.com | N31: TUV | O31: https://www.medzell.net/company/alliance-elemech/ | Q31: 45 | R31: =IF(Q31="","",IF(Q31>=60,"HIGH",IF(Q31>=30,"MEDIUM","LOW"))) | S31: New | T31: 2026-03-05 | U31: Seed=Medzell; Seed-file: output/medzell_company_urls.txt
A32: 31 | B32: Leading Manufacturer and Exporter of Hospital Equipment - Allied Medical Limited (AML) | D32: Manufacturer | E32: PPE | F32: Wound Care, Lab Consumables, Syringes & Needles, IV Infusion Sets, Gauze & Bandages, Disinfectants, IV Cannulas, Catheters | H32: https://www.medzell.net/main-categories-application/therapeutic-devices/ | I32: godwin@alliedmed.co.in | L32: Stated | M32: Stated | N32: FDA, TUV | O32: https://www.medzell.net/company/allied-medical-ltd/ | Q32: 0 | R32: =IF(Q32="","",IF(Q32>=60,"HIGH",IF(Q32>=30,"MEDIUM","LOW"))) | S32: New | T32: 2026-03-05 | U32: Seed=Medzell; Seed-file: output/medzell_company_urls.txt
A33: 32 | B33: Alpine Biomedicals – Advancing Rapid Diagnostics for Accurate & Cost-Effective Healthcare Solutions | D33: Manufacturer | E33: PPE | F33: Wound Care, Lab Consumables, Syringes & Needles, IV Infusion Sets, Gauze & Bandages, Disinfectants, IV Cannulas, Catheters | H33: https://www.medzell.net/main-categories-application/therapeutic-devices/ | I33: sales@alpinebiomedicals.com | L33: Stated | N33: TUV | O33: https://www.medzell.net/company/alpine-biomedicals-pvt-ltd/ | Q33: 10 | R33: =IF(Q33="","",IF(Q33>=60,"HIGH",IF(Q33>=30,"MEDIUM","LOW"))) | S33: New | T33: 2026-03-05 | U33: Seed=Medzell; Seed-file: output/medzell_company_urls.txt
A34: 33 | B34: Altis Instruments - Trusted Lab Furnaces, Ovens & Sterilizer Solutions | D34: Manufacturer | E34: PPE | F34: Wound Care, Lab Consumables, Syringes & Needles, IV Infusion Sets, Gauze & Bandages, Disinfectants, IV Cannulas, Catheters | H34: https://www.medzell.net/main-categories-application/therapeutic-devices/ | I34: altisinstrumentsindia@gmail.com | L34: Stated | N34: FDA, GMP, TUV | O34: https://www.medzell.net/company/altis-instruments/ | Q34: 30 | R34: =IF(Q34="","",IF(Q34>=60,"HIGH",IF(Q34>=30,"MEDIUM","LOW"))) | S34: New | T34: 2026-03-05 | U34: Seed=Medzell; Seed-file: output/medzell_company_urls.txt
A35: 34 | B35: Amazing Rubber Products – Premium Medical Gloves for Global Healthcare | D35: Manufacturer | E35: PPE | F35: Wound Care, Lab Consumables, Syringes & Needles, IV Infusion Sets, Gloves, Gauze & Bandages, Disinfectants, IV Cannulas, Catheters | H35: https://www.medzell.net/main-categories-application/therapeutic-devices/ | I35: inquiries@amazingglove.com | L35: Stated | N35: FDA, GMP, TUV | O35: https://www.medzell.net/company/amazing-rubber-products-pvt-ltd/ | Q35: 10 | R35: =IF(Q35="","",IF(Q35>=60,"HIGH",IF(Q35>=30,"MEDIUM","LOW"))) | S35: New | T35: 2026-03-05 | U35: Seed=Medzell; Seed-file: output/medzell_company_urls.txt
A36: 35 | B36: AMBELIO - Innovative Medical Devices for Pain Management | D36: Manufacturer | E36: PPE | F36: Wound Care, Lab Consumables, Syringes & Needles, IV Infusion Sets, Gauze & Bandages, Disinfectants, IV Cannulas, Catheters | H36: https://www.medzell.net/main-categories-application/therapeutic-devices/ | I36: achats@ambelio.com | N36: TUV | O36: https://www.medzell.net/company/ambelio/ | Q36: 25 | R36: =IF(Q36="","",IF(Q36>=60,"HIGH",IF(Q36>=30,"MEDIUM","LOW"))) | S36: New | T36: 2026-03-05 | U36: Seed=Medzell; Seed-file: output/medzell_company_urls.txt
A37: 36 | B37: Eqwell – Your Reliable Partner for Surgical Dressings & Medical Supplies | D37: Manufacturer | E37: PPE | F37: Wound Care, Gauze & Bandages, Lab Consumables, Syringes & Needles, IV Infusion Sets, Disinfectants, IV Cannulas, Catheters | H37: https://www.medzell.net/main-categories-application/therapeutic-devices/ | I37: ambikatraders555@gmail.com | N37: TUV | O37: https://www.medzell.net/company/ambika-traders-eqwell/ | Q37: 45 | R37: =IF(Q37="","",IF(Q37>=60,"HIGH",IF(Q37>=30,"MEDIUM","LOW"))) | S37: New | T37: 2026-03-05 | U37: Seed=Medzell; Seed-file: output/medzell_company_urls.txt
A38: 37 | B38: Ambinova Technologies: Precision-Engineered Laboratory Solutions | D38: Manufacturer | E38: PPE | F38: Wound Care, Lab Consumables, Syringes & Needles, IV Infusion Sets, Gauze & Bandages, Disinfectants, IV Cannulas, Catheters | H38: https://www.medzell.net/main-categories-application/therapeutic-devices/ | I38: paul@ambinova.in | N38: TUV | O38: https://www.medzell.net/company/ambinova-technologies-pvt-ltd/ | Q38: 25 | R38: =IF(Q38="","",IF(Q38>=60,"HIGH",IF(Q38>=30,"MEDIUM","LOW"))) | S38: New | T38: 2026-03-05 | U38: Seed=Medzell; Seed-file: output/medzell_company_urls.txt
A39: 38 | B39: Leading Manufacturer of Medical Tubing and Consumables - Ami Polymer Pvt. Ltd. | D39: Manufacturer | E39: PPE | F39: Wound Care, Lab Consumables, Syringes & Needles, IV Cannulas, IV Infusion Sets, Gauze & Bandages, Disinfectants, Catheters | H39: https://www.medzell.net/main-categories-application/therapeutic-devices/ | I39: anuj.s@amipolymer.com | L39: Stated | N39: FDA, TUV | O39: https://www.medzell.net/company/ami-polymer-pvt-ltd/ | Q39: 10 | R39: =IF(Q39="","",IF(Q39>=60,"HIGH",IF(Q39>=30,"MEDIUM","LOW"))) | S39: New | T39: 2026-03-05 | U39: Seed=Medzell; Seed-file: output/medzell_company_urls.txt
A40: 39 | B40: AMX Medical Systems: Top Manufacturer & Supplier of Advanced X-Ray Machines | D40: Manufacturer | E40: PPE | F40: Wound Care, Lab Consumables, Syringes & Needles, IV Infusion Sets, Gauze & Bandages, Disinfectants, IV Cannulas, Catheters | H40: https://www.medzell.net/main-categories-application/therapeutic-devices/ | I40: amxmedicalsystems@gmail.com | L40: Stated | N40: TUV | O40: https://www.medzell.net/company/amx-medical-systems/ | Q40: 30 | R40: =IF(Q40="","",IF(Q40>=60,"HIGH",IF(Q40>=30,"MEDIUM","LOW"))) | S40: New | T40: 2026-03-05 | U40: Seed=Medzell; Seed-file: output/medzell_company_urls.txt
A41: 40 | B41: Anand Surgical Industries India: Leading Manufacturer & Exporter of Hospital Furniture & Equipment | D41: Manufacturer | E41: PPE | F41: Wound Care, Lab Consumables, Syringes & Needles, IV Infusion Sets, Gauze & Bandages, Disinfectants, IV Cannulas, Catheters | H41: https://www.medzell.net/main-categories-application/therapeutic-devices/ | I41: sarthakv01@gmail.com | N41: TUV | O41: https://www.medzell.net/company/anand-surgical-industries-india-surgix/ | Q41: 45 | R41: =IF(Q41="","",IF(Q41>=60,"HIGH",IF(Q41>=30,"MEDIUM","LOW"))) | S41: New | T41: 2026-03-05 | U41: Seed=Medzell; Seed-file: output/medzell_company_urls.txt
A42: 41 | B42: Henan Anbang Medical Supplies: Leading Manufacturer of Medical & Surgical Disposables | D42: Manufacturer | E42: PPE | F42: Wound Care, Lab Consumables, Syringes & Needles, IV Infusion Sets, Gauze & Bandages, Disinfectants, IV Cannulas, Catheters | H42: https://www.medzell.net/main-categories-application/therapeutic-devices/ | I42: mia@anbangmedical.com | L42: Stated | N42: TUV | O42: https://www.medzell.net/company/anbang-medical-supplies/ | Q42: 10 | R42: =IF(Q42="","",IF(Q42>=60,"HIGH",IF(Q42>=30,"MEDIUM","LOW"))) | S42: New | T42: 2026-03-05 | U42: Seed=Medzell; Seed-file: output/medzell_company_urls.txt
A43: 42 | B43: Angiplast Private Limited: Leading Medical Device Manufacturers in India | D43: Manufacturer | E43: PPE | F43: Catheters, Wound Care, Syringes & Needles, IV Infusion Sets, Lab Consumables, IV Cannulas, Gauze & Bandages, Disinfectants, Gloves | H43: https://www.medzell.net/main-categories-application/therapeutic-devices/ | I43: marketing@angiplast.com | L43: Stated | M43: Stated | N43: FDA, GMP, TUV | O43: https://www.medzell.net/company/angiplast-private-limited/ | Q43: 0 | R43: =IF(Q43="","",IF(Q43>=60,"HIGH",IF(Q43>=30,"MEDIUM","LOW"))) | S43: New | T43: 2026-03-05 | U43: Seed=Medzell; Seed-file: output/medzell_company_urls.txt
A44: 43 | B44: Anigma Enterprise: Leading Manufacturer & Global Supplier of Laparoscopic Instruments in India | D44: Manufacturer | E44: PPE | F44: Wound Care, Lab Consumables, Syringes & Needles, IV Infusion Sets, Gauze & Bandages, Disinfectants, IV Cannulas, Catheters | H44: https://www.medzell.net/main-categories-application/therapeutic-devices/ | I44: anigmaexports@gmail.com | N44: FDA, GMP, TUV | O44: https://www.medzell.net/company/anigma-enterprise/ | Q44: 45 | R44: =IF(Q44="","",IF(Q44>=60,"HIGH",IF(Q44>=30,"MEDIUM","LOW"))) | S44: New | T44: 2026-03-05 | U44: Seed=Medzell; Seed-file: output/medzell_company_urls.txt
A45: 44 | B45: Anping Guardian Medical Equipment Co., Ltd. – Premium Emergency Medical Products | OEM/ODM Manufacturer of First Aid Kits & More Ask ChatGPT | D45: Manufacturer | E45: PPE | F45: Wound Care, Lab Consumables, Syringes & Needles, IV Infusion Sets, Gauze & Bandages, Disinfectants, IV Cannulas, Catheters | H45: https://www.medzell.net/main-categories-application/therapeutic-devices/ | I45: sales4@splint.cn | L45: Stated | N45: TUV | O45: https://www.medzell.net/company/anping-guardian-medical-equipment-co-ltd/ | Q45: 10 | R45: =IF(Q45="","",IF(Q45>=60,"HIGH",IF(Q45>=30,"MEDIUM","LOW"))) | S45: New | T45: 2026-03-05 | U45: Seed=Medzell; Seed-file: output/medzell_company_urls.txt
A46: 45 | B46: AoneS Labs: Leading Manufacturer & Exporter of High-Quality Medical Devices | D46: Manufacturer | E46: PPE | F46: Wound Care, Lab Consumables, Syringes & Needles, IV Infusion Sets, Gauze & Bandages, Disinfectants, IV Cannulas, Catheters | H46: https://www.medzell.net/main-categories-application/therapeutic-devices/ | I46: sayalit@crescendoworldwide.org | L46: Stated | N46: TUV | O46: https://www.medzell.net/company/aones-labs/ | Q46: 10 | R46: =IF(Q46="","",IF(Q46>=60,"HIGH",IF(Q46>=30,"MEDIUM","LOW"))) | S46: New | T46: 2026-03-05 | U46: Seed=Medzell; Seed-file: output/medzell_company_urls.txt
A47: 46 | B47: High-Quality Medical Devices for Orthopedic Rehabilitation and Oncology Needs | Arambans Exporters (Pvt) Ltd. | D47: Manufacturer | E47: PPE | F47: Gauze & Bandages, Wound Care, Gloves, Lab Consumables, Syringes & Needles, IV Infusion Sets, Disinfectants, IV Cannulas, Catheters | H47: https://www.medzell.net/main-categories-application/therapeutic-devices/ | I47: careforindiaenq@gmail.com | L47: Stated | N47: TUV | O47: https://www.medzell.net/company/arambans-exporters-pvt-ltd/ | Q47: 30 | R47: =IF(Q47="","",IF(Q47>=60,"HIGH",IF(Q47>=30,"MEDIUM","LOW"))) | S47: New | T47: 2026-03-05 | U47: Seed=Medzell; Seed-file: output/medzell_company_urls.txt
A48: 47 | B48: Revolutionizing Assisted Living: Arcatron Mobility - Innovative Solutions for Rehabilitation & Physiotherapy Devices | D48: Manufacturer | E48: PPE | F48: Wound Care, Lab Consumables, Syringes & Needles, IV Infusion Sets, Gauze & Bandages, Disinfectants, IV Cannulas, Catheters | H48: https://www.medzell.net/main-categories-application/therapeutic-devices/ | I48: savio.a@arcatron.com | N48: FDA, TUV | O48: https://www.medzell.net/company/arcatron-mobility-private-limited/ | Q48: 25 | R48: =IF(Q48="","",IF(Q48>=60,"HIGH",IF(Q48>=30,"MEDIUM","LOW"))) | S48: New | T48: 2026-03-05 | U48: Seed=Medzell; Seed-file: output/medzell_company_urls.txt
A49: 48 | B49: ARVS Equipments: Leading Manufacturer of Biomedical Waste Management Products | D49: Manufacturer | E49: PPE | F49: Wound Care, Lab Consumables, Syringes & Needles, IV Infusion Sets, Gauze & Bandages, Disinfectants, IV Cannulas, Catheters | H49: https://www.medzell.net/main-categories-application/therapeutic-devices/ | I49: dilip@arvsequipments.com | L49: Stated | N49: TUV | O49: https://www.medzell.net/company/arvs-equipments-private-limited/ | Q49: 10 | R49: =IF(Q49="","",IF(Q49>=60,"HIGH",IF(Q49>=30,"MEDIUM","LOW"))) | S49: New | T49: 2026-03-05 | U49: Seed=Medzell; Seed-file: output/medzell_company_urls.txt
A50: 49 | B50: High-Quality Hospital Furniture Manufacturer & Supplier in India - A.S Medisteel | D50: Manufacturer | E50: PPE | F50: Wound Care, Lab Consumables, Syringes & Needles, IV Infusion Sets, Gauze & Bandages, Disinfectants, IV Cannulas, Catheters | H50: https://www.medzell.net/main-categories-application/therapeutic-devices/ | I50: amarjeetmishra7@gmail.com | N50: GMP, TUV | O50: https://www.medzell.net/company/as-medisteel/ | Q50: 45 | R50: =IF(Q50="","",IF(Q50>=60,"HIGH",IF(Q50>=30,"MEDIUM","LOW"))) | S50: New | T50: 2026-03-05 | U50: Seed=Medzell; Seed-file: output/medzell_company_urls.txt
A51: 50 | B51: High-Quality Ophthalmic Equipment and Consumables | A.S.F. Universal | D51: Manufacturer | E51: PPE | F51: Wound Care, Lab Consumables, Syringes & Needles, IV Infusion Sets, Gauze & Bandages, Disinfectants, IV Cannulas, Catheters | H51: https://www.medzell.net/main-categories-application/therapeutic-devices/ | I51: asfuniversalx2@gmail.com | L51: Stated | N51: TUV | O51: https://www.medzell.net/company/asf-universal/ | Q51: 30 | R51: =IF(Q51="","",IF(Q51>=60,"HIGH",IF(Q51>=30,"MEDIUM","LOW"))) | S51: New | T51: 2026-03-05 | U51: Seed=Medzell; Seed-file: output/medzell_company_urls.txt
A52: 51 | B52: High-Quality Healthcare and Medical Products | ASKP Solutions | D52: Manufacturer | E52: Catheters | F52: PPE, Wound Care, Lab Consumables, Syringes & Needles, IV Infusion Sets, Gauze & Bandages, Disinfectants, IV Cannulas | H52: https://www.medzell.net/main-categories-application/therapeutic-devices/ | I52: askpsolutions@gmail.com | L52: Stated | M52: Stated | N52: TUV | O52: https://www.medzell.net/company/askp-solutions/ | Q52: 20 | R52: =IF(Q52="","",IF(Q52>=60,"HIGH",IF(Q52>=30,"MEDIUM","LOW"))) | S52: New | T52: 2026-03-05 | U52: Seed=Medzell; Seed-file: output/medzell_company_urls.txt
A53: 52 | B53: Aspinwall Healthcare | Leading Manufacturer of Ligation Devices | D53: Manufacturer | E53: PPE | F53: Wound Care, Lab Consumables, Syringes & Needles, IV Infusion Sets, Gauze & Bandages, Disinfectants, IV Cannulas, Catheters | H53: https://www.medzell.net/main-categories-application/therapeutic-devices/ | I53: arunmidevices@gmail.com | L53: Stated | N53: TUV | O53: https://www.medzell.net/company/aspinwall-healthcare-pvt-ltd/ | Q53: 30 | R53: =IF(Q53="","",IF(Q53>=60,"HIGH",IF(Q53>=30,"MEDIUM","LOW"))) | S53: New | T53: 2026-03-05 | U53: Seed=Medzell; Seed-file: output/medzell_company_urls.txt
A54: 53 | B54: Aston Vision Sciences | Pioneering Accessible Eye Care Technology | D54: Manufacturer | E54: PPE | F54: Wound Care, Lab Consumables, Syringes & Needles, IV Infusion Sets, Gauze & Bandages, Disinfectants, IV Cannulas, Catheters | H54: https://www.medzell.net/main-categories-application/therapeutic-devices/ | I54: karl@astonvisionsciences.com | L54: Stated | N54: TUV | O54: https://www.medzell.net/company/aston-vision-sciences/ | Q54: 10 | R54: =IF(Q54="","",IF(Q54>=60,"HIGH",IF(Q54>=30,"MEDIUM","LOW"))) | S54: New | T54: 2026-03-05 | U54: Seed=Medzell; Seed-file: output/medzell_company_urls.txt
A55: 54 | B55: Auctus Healthcare: Your Ultimate Source for Medical Needs & Covid-19 Protection | D55: Manufacturer | E55: PPE | F55: Wound Care, Gloves, Lab Consumables, Syringes & Needles, IV Infusion Sets, Gauze & Bandages, Disinfectants, IV Cannulas, Catheters | H55: https://www.medzell.net/main-categories-application/therapeutic-devices/ | I55: info@auctushealthcare.com | N55: TUV | O55: https://www.medzell.net/company/auctus-healthcare-general-pvt-ltd/ | Q55: 25 | R55: =IF(Q55="","",IF(Q55>=60,"HIGH",IF(Q55>=30,"MEDIUM","LOW"))) | S55: New | T55: 2026-03-05 | U55: Seed=Medzell; Seed-file: output/medzell_company_urls.txt
A56: 55 | B56: Premium Ophthalmic Consumables and Medical Devices | Aurolab | D56: Manufacturer | E56: PPE | F56: Wound Care, Disinfectants, Lab Consumables, Syringes & Needles, IV Infusion Sets, Gauze & Bandages, IV Cannulas, Catheters | H56: https://www.medzell.net/main-categories-application/therapeutic-devices/ | I56: avsight@gmail.com | L56: Stated | N56: FDA, GMP, TUV | O56: https://www.medzell.net/company/aurolab/ | Q56: 30 | R56: =IF(Q56="","",IF(Q56>=60,"HIGH",IF(Q56>=30,"MEDIUM","LOW"))) | S56: New | T56: 2026-03-05 | U56: Seed=Medzell; Seed-file: output/medzell_company_urls.txt
A57: 56 | B57: Aurus MedTech: Premier Manufacturer and Global Supplier of Cutting-Edge Medical and Surgical Consumables | D57: Manufacturer | E57: PPE | F57: Wound Care, Catheters, Lab Consumables, Syringes & Needles, IV Cannulas, IV Infusion Sets, Gauze & Bandages, Disinfectants | H57: https://www.medzell.net/main-categories-application/therapeutic-devices/ | I57: pushvender.sales@aurusmedtech.com | L57: Stated | N57: GMP, TUV | O57: https://www.medzell.net/company/aurus-medtech-pvt-ltd/ | Q57: 10 | R57: =IF(Q57="","",IF(Q57>=60,"HIGH",IF(Q57>=30,"MEDIUM","LOW"))) | S57: New | T57: 2026-03-05 | U57: Seed=Medzell; Seed-file: output/medzell_company_urls.txt
A58: 57 | B58: Avecon Healthcare Private Limited | D58: Manufacturer | E58: PPE | F58: Wound Care, Lab Consumables, Syringes & Needles, IV Infusion Sets, Gauze & Bandages, Disinfectants, IV Cannulas, Catheters | H58: https://www.medzell.net/main-categories-application/therapeutic-devices/ | I58: prabhat@aveconhealthcare.com | L58: Stated | N58: TUV | O58: https://www.medzell.net/company/avecon-healthcare-pvt-ltd/ | Q58: 10 | R58: =IF(Q58="","",IF(Q58>=60,"HIGH",IF(Q58>=30,"MEDIUM","LOW"))) | S58: New | T58: 2026-03-05 | U58: Seed=Medzell; Seed-file: output/medzell_company_urls.txt
A59: 58 | B59: Affordable and Innovative Medical Equipment by AVI Healthcare Pvt. Ltd. | D59: Manufacturer | E59: PPE | F59: Wound Care, Lab Consumables, Syringes & Needles, IV Infusion Sets, Gauze & Bandages, Disinfectants, IV Cannulas, Catheters | H59: https://www.medzell.net/main-categories-application/therapeutic-devices/ | I59: sales@avihealthcare.com | L59: Stated | N59: TUV | O59: https://www.medzell.net/company/avi-healthcare-pvt-ltd/ | Q59: 10 | R59: =IF(Q59="","",IF(Q59>=60,"HIGH",IF(Q59>=30,"MEDIUM","LOW"))) | S59: New | T59: 2026-03-05 | U59: Seed=Medzell; Seed-file: output/medzell_company_urls.txt
A60: 59 | B60: Leading Manufacturer of Biomaterial-Based Medical Devices | Axio Biosolutions | D60: Manufacturer | E60: PPE | F60: Wound Care, Lab Consumables, Syringes & Needles, IV Infusion Sets, Gauze & Bandages, Disinfectants, IV Cannulas, Catheters | H60: https://www.medzell.net/main-categories-application/therapeutic-devices/ | I60: william.r@axiobio.com | L60: Stated | M60: Stated | N60: FDA, GMP, TUV | O60: https://www.medzell.net/company/axio-biosolutions-private-limited/ | Q60: 0 | R60: =IF(Q60="","",IF(Q60>=60,"HIGH",IF(Q60>=30,"MEDIUM","LOW"))) | S60: New | T60: 2026-03-05 | U60: Seed=Medzell; Seed-file: output/medzell_company_urls.txt
A61: 60 | B61: Discover Cutting-Edge Medical Devices and Solutions with Axon Medical Solutions - India's Premier Manufacturer and Global Supplier | D61: Manufacturer | E61: PPE | F61: Wound Care, Lab Consumables, Syringes & Needles, IV Infusion Sets, Gauze & Bandages, Disinfectants, IV Cannulas, Catheters | H61: https://www.medzell.net/main-categories-application/therapeutic-devices/ | I61: info@axonmedicalsolutions.com | L61: Stated | N61: FDA, TUV | O61: https://www.medzell.net/company/axon-medical-solutions/ | Q61: 10 | R61: =IF(Q61="","",IF(Q61>=60,"HIGH",IF(Q61>=30,"MEDIUM","LOW"))) | S61: New | T61: 2026-03-05 | U61: Seed=Medzell; Seed-file: output/medzell_company_urls.txt
A62: 61 | B62: Balaji Surgical – Leading Provider of OT Room Equipment and Medical Devices | D62: Manufacturer | E62: PPE | F62: Wound Care, Lab Consumables, Syringes & Needles, IV Infusion Sets, Gauze & Bandages, Disinfectants, IV Cannulas, Catheters | H62: https://www.medzell.net/main-categories-application/therapeutic-devices/ | I62: info@balajisurgical.com | L62: Stated | N62: GMP, TUV | O62: https://www.medzell.net/company/balaji-surgical/ | Q62: 10 | R62: =IF(Q62="","",IF(Q62>=60,"HIGH",IF(Q62>=30,"MEDIUM","LOW"))) | S62: New | T62: 2026-03-05 | U62: Seed=Medzell; Seed-file: output/medzell_company_urls.txt
A63: 62 | B63: Transform Your Healthcare Facility with BBM Healthcare's Innovative Hospital Management Systems | D63: Manufacturer | E63: PPE | F63: Wound Care, Lab Consumables, Syringes & Needles, IV Infusion Sets, Gauze & Bandages, Disinfectants, IV Cannulas, Catheters | H63: https://www.medzell.net/main-categories-application/therapeutic-devices/ | I63: Bbmhealthcare@gmail.com | N63: TUV | O63: https://www.medzell.net/company/bbm-healthcare/ | Q63: 45 | R63: =IF(Q63="","",IF(Q63>=60,"HIGH",IF(Q63>=30,"MEDIUM","LOW"))) | S63: New | T63: 2026-03-05 | U63: Seed=Medzell; Seed-file: output/medzell_company_urls.txt
A64: 63 | B64: Bercon Medical Device Co., Ltd. : Leading Manufacturer of Infusion Systems, Patient Monitoring & Respiratory Care | D64: Manufacturer | E64: PPE | F64: Wound Care, Lab Consumables, Syringes & Needles, IV Infusion Sets, Gauze & Bandages, Disinfectants, IV Cannulas, Catheters | H64: https://www.medzell.net/main-categories-application/therapeutic-devices/ | I64: sophia9903@gmail.com | L64: Stated | M64: Stated | N64: TUV | O64: https://www.medzell.net/company/bercon-medical/ | Q64: 20 | R64: =IF(Q64="","",IF(Q64>=60,"HIGH",IF(Q64>=30,"MEDIUM","LOW"))) | S64: New | T64: 2026-03-05 | U64: Seed=Medzell; Seed-file: output/medzell_company_urls.txt
A65: 64 | B65: Top Manufacturer of High-Quality Medical Gloves in India - Beta Healthcare Products Pvt. Ltd. | D65: Manufacturer | E65: PPE | F65: Wound Care, Lab Consumables, Syringes & Needles, IV Infusion Sets, Gloves, Gauze & Bandages, Disinfectants, IV Cannulas, Catheters | H65: https://www.medzell.net/main-categories-application/therapeutic-devices/ | I65: cherian@betahealthcare.com | L65: Stated | N65: FDA, GMP, TUV | O65: https://www.medzell.net/company/beta-healthcare-products-pvt-ltd/ | Q65: 10 | R65: =IF(Q65="","",IF(Q65>=60,"HIGH",IF(Q65>=30,"MEDIUM","LOW"))) | S65: New | T65: 2026-03-05 | U65: Seed=Medzell; Seed-file: output/medzell_company_urls.txt
A66: 65 | B66: Leading Manufacturer and Supplier of Disposable Drapes and Surgical Kits - Bio-Hyginx Pvt. Ltd. | D66: Manufacturer | E66: PPE | F66: Wound Care, Lab Consumables, Syringes & Needles, IV Infusion Sets, Gauze & Bandages, Disinfectants, IV Cannulas, Catheters | H66: https://www.medzell.net/main-categories-application/therapeutic-devices/ | I66: bihyc111@gmail.com | L66: Stated | M66: Stated | N66: GMP, TUV | O66: https://www.medzell.net/company/bio-hyginx-pvt-ltd/ | Q66: 20 | R66: =IF(Q66="","",IF(Q66>=60,"HIGH",IF(Q66>=30,"MEDIUM","LOW"))) | S66: New | T66: 2026-03-05 | U66: Seed=Medzell; Seed-file: output/medzell_company_urls.txt
A67: 66 | B67: Bio Medical Devices - Leading Manufacturer of SS Trocars and Wound Drainage Instruments | D67: Manufacturer | E67: PPE | F67: Wound Care, Lab Consumables, Syringes & Needles, IV Infusion Sets, Gauze & Bandages, Disinfectants, IV Cannulas, Catheters | H67: https://www.medzell.net/main-categories-application/therapeutic-devices/ | I67: hiten.biomedical@gmail.com | N67: TUV | O67: https://www.medzell.net/company/bio-medical-devices/ | Q67: 45 | R67: =IF(Q67="","",IF(Q67>=60,"HIGH",IF(Q67>=30,"MEDIUM","LOW"))) | S67: New | T67: 2026-03-05 | U67: Seed=Medzell; Seed-file: output/medzell_company_urls.txt
A68: 67 | B68: Top-Quality Modular Operation Theatres | BIO-X - Global Supplier | D68: Manufacturer | E68: PPE | F68: Wound Care, Lab Consumables, Syringes & Needles, IV Infusion Sets, Gauze & Bandages, Disinfectants, IV Cannulas, Catheters | H68: https://www.medzell.net/main-categories-application/therapeutic-devices/ | I68: biox@biox.co.in | L68: Stated | N68: TUV | O68: https://www.medzell.net/company/bio-x/ | Q68: 10 | R68: =IF(Q68="","",IF(Q68>=60,"HIGH",IF(Q68>=30,"MEDIUM","LOW"))) | S68: New | T68: 2026-03-05 | U68: Seed=Medzell; Seed-file: output/medzell_company_urls.txt
A69: 68 | B69: Top Medical Ventilators by Biodesign Innovation Labs for Healthcare | D69: Manufacturer | E69: PPE | F69: Wound Care, Lab Consumables, Syringes & Needles, IV Infusion Sets, Gauze & Bandages, Disinfectants, IV Cannulas, Catheters | H69: https://www.medzell.net/main-categories-application/therapeutic-devices/ | I69: gautham@biodesigninnovationlabs.com | N69: TUV | O69: https://www.medzell.net/company/biodesign-innovation-labs/ | Q69: 25 | R69: =IF(Q69="","",IF(Q69>=60,"HIGH",IF(Q69>=30,"MEDIUM","LOW"))) | S69: New | T69: 2026-03-05 | U69: Seed=Medzell; Seed-file: output/medzell_company_urls.txt
A70: 69 | B70: Bioline India | D70: Manufacturer | E70: PPE | F70: Wound Care, Lab Consumables, Syringes & Needles, IV Infusion Sets, Gauze & Bandages, Disinfectants, IV Cannulas, Catheters | H70: https://www.medzell.net/main-categories-application/therapeutic-devices/ | I70: biolineindia@yahoo.co.in | L70: Stated | N70: TUV | O70: https://www.medzell.net/company/bioline-india/ | Q70: 10 | R70: =IF(Q70="","",IF(Q70>=60,"HIGH",IF(Q70>=30,"MEDIUM","LOW"))) | S70: New | T70: 2026-03-05 | U70: Seed=Medzell; Seed-file: output/medzell_company_urls.txt
A71: 70 | B71: Biomed Healthtech Pvt. Ltd. | Quality Orthopedic Implants | D71: Manufacturer | E71: PPE | F71: Wound Care, Lab Consumables, Syringes & Needles, IV Infusion Sets, Gauze & Bandages, Disinfectants, IV Cannulas, Catheters | H71: https://www.medzell.net/main-categories-application/therapeutic-devices/ | I71: pkumar@biomedorthopedics.com | L71: Stated | N71: TUV | O71: https://www.medzell.net/company/biomed-healthtech-pvt-ltd/ | Q71: 10 | R71: =IF(Q71="","",IF(Q71>=60,"HIGH",IF(Q71>=30,"MEDIUM","LOW"))) | S71: New | T71: 2026-03-05 | U71: Seed=Medzell; Seed-file: output/medzell_company_urls.txt
A72: 71 | B72: Robo Bionics: Innovative Lightweight Bionic Hands - Advanced Touch, Quick Learning, Affordable Solutions | D72: Manufacturer | E72: PPE | F72: Wound Care, Lab Consumables, Syringes & Needles, IV Infusion Sets, Gauze & Bandages, Disinfectants, IV Cannulas, Catheters | H72: https://www.medzell.net/main-categories-application/therapeutic-devices/ | I72: purchase@robobionics.in | N72: TUV | O72: https://www.medzell.net/company/bionic-hope-private-limited/ | Q72: 25 | R72: =IF(Q72="","",IF(Q72>=60,"HIGH",IF(Q72>=30,"MEDIUM","LOW"))) | S72: New | T72: 2026-03-05 | U72: Seed=Medzell; Seed-file: output/medzell_company_urls.txt
A73: 72 | B73: Biophoton Technologies | Affordable Bio-Photonics Solutions for Newborn Therapy | D73: Manufacturer | E73: PPE | F73: Wound Care, Lab Consumables, Syringes & Needles, IV Infusion Sets, Gauze & Bandages, Disinfectants, IV Cannulas, Catheters | H73: https://www.medzell.net/main-categories-application/therapeutic-devices/ | I73: sales@biophotontechnologies.com | L73: Stated | N73: TUV | O73: https://www.medzell.net/company/biophoton-technologies-pvt-ltd/ | Q73: 10 | R73: =IF(Q73="","",IF(Q73>=60,"HIGH",IF(Q73>=30,"MEDIUM","LOW"))) | S73: New | T73: 2026-03-05 | U73: Seed=Medzell; Seed-file: output/medzell_company_urls.txt
A74: 73 | B74: BioScan AI: Advanced AI Solutions for Early Disease Detection & Improved Patient Outcomes | D74: Manufacturer | E74: PPE | F74: Wound Care, Lab Consumables, Syringes & Needles, IV Infusion Sets, Gauze & Bandages, Disinfectants, IV Cannulas, Catheters | H74: https://www.medzell.net/main-categories-application/therapeutic-devices/ | I74: varij.srivastava@bioscanai.com | N74: TUV | O74: https://www.medzell.net/company/bioscan-ai-innovative-solutions/ | Q74: 25 | R74: =IF(Q74="","",IF(Q74>=60,"HIGH",IF(Q74>=30,"MEDIUM","LOW"))) | S74: New | T74: 2026-03-05 | U74: Seed=Medzell; Seed-file: output/medzell_company_urls.txt
A75: 74 | B75: Affordable Medical Devices for Early Hemorrhage Detection - Bioscan Research | D75: Manufacturer | E75: PPE | F75: Wound Care, Lab Consumables, Syringes & Needles, IV Infusion Sets, Gauze & Bandages, Disinfectants, IV Cannulas, Catheters | H75: https://www.medzell.net/main-categories-application/therapeutic-devices/ | I75: partnerships@bioscanresearch.com | L75: Stated | N75: TUV | O75: https://www.medzell.net/company/bioscan-research-private-limited/ | Q75: 10 | R75: =IF(Q75="","",IF(Q75>=60,"HIGH",IF(Q75>=30,"MEDIUM","LOW"))) | S75: New | T75: 2026-03-05 | U75: Seed=Medzell; Seed-file: output/medzell_company_urls.txt
A76: 75 | B76: Biosysion | Advancing Molecular Diagnostics for Early Disease Detection | D76: Manufacturer | E76: PPE | F76: Wound Care, Lab Consumables, Syringes & Needles, IV Infusion Sets, Gauze & Bandages, Disinfectants, IV Cannulas, Catheters | H76: https://www.medzell.net/main-categories-application/therapeutic-devices/ | I76: info@biosystemvision.com | N76: TUV | O76: https://www.medzell.net/company/biosysion-private-limited/ | Q76: 25 | R76: =IF(Q76="","",IF(Q76>=60,"HIGH",IF(Q76>=30,"MEDIUM","LOW"))) | S76: New | T76: 2026-03-05 | U76: Seed=Medzell; Seed-file: output/medzell_company_urls.txt
A77: 76 | B77: Cutting-Edge Micropipettes by Biosystem Company: Precision and Excellence for Laboratory Liquid Handling | D77: Manufacturer | E77: PPE | F77: Wound Care, Lab Consumables, Syringes & Needles, IV Infusion Sets, Gauze & Bandages, Disinfectants, IV Cannulas, Catheters | H77: https://www.medzell.net/main-categories-application/therapeutic-devices/ | I77: biosystem2007@yahoo.com | L77: Stated | M77: Stated | N77: TUV | O77: https://www.medzell.net/company/biosystem-company/ | Q77: 20 | R77: =IF(Q77="","",IF(Q77>=60,"HIGH",IF(Q77>=30,"MEDIUM","LOW"))) | S77: New | T77: 2026-03-05 | U77: Seed=Medzell; Seed-file: output/medzell_company_urls.txt
A78: 77 | B78: Biowy Corporation: Pioneers in Advanced Medical and Biotech Solutions | D78: Manufacturer | E78: PPE | F78: Wound Care, Lab Consumables, Syringes & Needles, IV Infusion Sets, Gauze & Bandages, Disinfectants, IV Cannulas, Catheters | H78: https://www.medzell.net/main-categories-application/therapeutic-devices/ | I78: paul@biowy.com | L78: Stated | N78: TUV | O78: https://www.medzell.net/company/biowy-corporation/ | Q78: 10 | R78: =IF(Q78="","",IF(Q78>=60,"HIGH",IF(Q78>=30,"MEDIUM","LOW"))) | S78: New | T78: 2026-03-05 | U78: Seed=Medzell; Seed-file: output/medzell_company_urls.txt
A79: 78 | B79: Leading Manufacturer of Neonatal Medical Devices in India - Bird Meditech | D79: Manufacturer | E79: PPE | F79: Wound Care, Lab Consumables, Syringes & Needles, IV Infusion Sets, Gauze & Bandages, Disinfectants, IV Cannulas, Catheters | H79: https://www.medzell.net/main-categories-application/therapeutic-devices/ | I79: birdmeditech@gmail.com | L79: Stated | N79: TUV | O79: https://www.medzell.net/company/bird-meditech/ | Q79: 30 | R79: =IF(Q79="","",IF(Q79>=60,"HIGH",IF(Q79>=30,"MEDIUM","LOW"))) | S79: New | T79: 2026-03-05 | U79: Seed=Medzell; Seed-file: output/medzell_company_urls.txt
A80: 79 | B80: Ophthalmic Micro Surgical Knives & Related Consumables Manufacturer | D80: Manufacturer | E80: PPE | F80: Wound Care, Lab Consumables, Syringes & Needles, IV Infusion Sets, Gauze & Bandages, Disinfectants, IV Cannulas, Catheters | H80: https://www.medzell.net/main-categories-application/therapeutic-devices/ | I80: blinkmedicas@gmail.com | L80: Stated | N80: TUV | O80: https://www.medzell.net/company/blink-medicas-ind/ | Q80: 30 | R80: =IF(Q80="","",IF(Q80>=60,"HIGH",IF(Q80>=30,"MEDIUM","LOW"))) | S80: New | T80: 2026-03-05 | U80: Seed=Medzell; Seed-file: output/medzell_company_urls.txt
A81: 80 | B81: Discover Excellence in Laparoscopic Instruments with Blue Phoenix Technologies Pvt. Ltd. | D81: Manufacturer | E81: PPE | F81: Wound Care, Lab Consumables, Syringes & Needles, IV Infusion Sets, Gauze & Bandages, Disinfectants, IV Cannulas, Catheters | H81: https://www.medzell.net/main-categories-application/therapeutic-devices/ | I81: bluephoenixmedi@gmail.com | L81: Stated | N81: TUV | O81: https://www.medzell.net/company/blue-phoenix-technologies-pvt-ltd/ | Q81: 30 | R81: =IF(Q81="","",IF(Q81>=60,"HIGH",IF(Q81>=30,"MEDIUM","LOW"))) | S81: New | T81: 2026-03-05 | U81: Seed=Medzell; Seed-file: output/medzell_company_urls.txt
A82: 81 | B82: Bontech | Innovating Digital X-Ray Solutions for Healthcare & Security | D82: Manufacturer | E82: PPE | F82: Wound Care, Lab Consumables, Syringes & Needles, IV Infusion Sets, Gauze & Bandages, Disinfectants, IV Cannulas, Catheters | H82: https://www.medzell.net/main-categories-application/therapeutic-devices/ | I82: farrukh@bontech.co | L82: Stated | N82: FDA, GMP, TUV | O82: https://www.medzell.net/company/bontech-co-ltd/ | Q82: 10 | R82: =IF(Q82="","",IF(Q82>=60,"HIGH",IF(Q82>=30,"MEDIUM","LOW"))) | S82: New | T82: 2026-03-05 | U82: Seed=Medzell; Seed-file: output/medzell_company_urls.txt
A83: 82 | B83: Borg Scientific: Leading Manufacturer & Global Supplier of Laboratory Devices Since 2001 | D83: Manufacturer | E83: PPE | F83: Wound Care, Lab Consumables, Syringes & Needles, IV Infusion Sets, Gauze & Bandages, Disinfectants, IV Cannulas, Catheters | H83: https://www.medzell.net/main-categories-application/therapeutic-devices/ | I83: info@borgscientific.com | N83: TUV | O83: https://www.medzell.net/company/borg-scientific/ | Q83: 25 | R83: =IF(Q83="","",IF(Q83>=60,"HIGH",IF(Q83>=30,"MEDIUM","LOW"))) | S83: New | T83: 2026-03-05 | U83: Seed=Medzell; Seed-file: output/medzell_company_urls.txt
A84: 83 | B84: BPL Medical Technologies: High-Quality Patient Care Products & Systems | ISO Certified | D84: Manufacturer | E84: PPE | F84: Wound Care, Lab Consumables, Syringes & Needles, IV Infusion Sets, Gauze & Bandages, Disinfectants, IV Cannulas, Catheters | H84: https://www.medzell.net/main-categories-application/therapeutic-devices/ | I84: sunil.prabhakar@bpl.in | L84: Stated | M84: Stated | N84: TUV | O84: https://www.medzell.net/company/bpl-medical-technologies/ | Q84: 0 | R84: =IF(Q84="","",IF(Q84>=60,"HIGH",IF(Q84>=30,"MEDIUM","LOW"))) | S84: New | T84: 2026-03-05 | U84: Seed=Medzell; Seed-file: output/medzell_company_urls.txt
A85: 84 | B85: Leading Manufacturer and Supplier of Laboratory Equipment in India - BR Biochem Life Sciences Pvt. Ltd. | D85: Manufacturer | E85: PPE | F85: Wound Care, Lab Consumables, Syringes & Needles, IV Infusion Sets, Gauze & Bandages, Disinfectants, IV Cannulas, Catheters, Gloves | H85: https://www.medzell.net/main-categories-application/therapeutic-devices/ | I85: info@brbls.com | M85: Stated | N85: TUV | O85: https://www.medzell.net/company/br-biochem-life-sciences-pvt-ltd/ | Q85: 15 | R85: =IF(Q85="","",IF(Q85>=60,"HIGH",IF(Q85>=30,"MEDIUM","LOW"))) | S85: New | T85: 2026-03-05 | U85: Seed=Medzell; Seed-file: output/medzell_company_urls.txt
A86: 85 | B86: Breathe Medical Systems: Leading Manufacturer of Cutting-Edge Infant and Maternal Care Products | D86: Manufacturer | E86: PPE | F86: Wound Care, Lab Consumables, Syringes & Needles, IV Infusion Sets, Gauze & Bandages, Disinfectants, IV Cannulas, Catheters | H86: https://www.medzell.net/main-categories-application/therapeutic-devices/ | I86: info@breathemedicalsystems.com | L86: Stated | N86: TUV | O86: https://www.medzell.net/company/breathe-medical-systems/ | Q86: 10 | R86: =IF(Q86="","",IF(Q86>=60,"HIGH",IF(Q86>=30,"MEDIUM","LOW"))) | S86: New | T86: 2026-03-05 | U86: Seed=Medzell; Seed-file: output/medzell_company_urls.txt
A87: 86 | B87: CareNX Innovations: Award-Winning Digital Healthcare Solutions for Pregnancy Care | D87: Manufacturer | E87: PPE | F87: Wound Care, Lab Consumables, Syringes & Needles, IV Infusion Sets, Gauze & Bandages, Disinfectants, IV Cannulas, Catheters | H87: https://www.medzell.net/main-categories-application/therapeutic-devices/ | I87: aditya@carenx.com | L87: Stated | N87: TUV | O87: https://www.medzell.net/company/carenx-innovations-private-limited/ | Q87: 10 | R87: =IF(Q87="","",IF(Q87>=60,"HIGH",IF(Q87>=30,"MEDIUM","LOW"))) | S87: New | T87: 2026-03-05 | U87: Seed=Medzell; Seed-file: output/medzell_company_urls.txt
A88: 87 | B88: Top-Notch Single-Use Medical Gear for Hospital Infection Control - Careon Healthcare Solutions Pvt. Ltd. | D88: Manufacturer | E88: PPE | F88: Wound Care, Lab Consumables, Syringes & Needles, IV Infusion Sets, Gauze & Bandages, Disinfectants, IV Cannulas, Catheters | H88: https://www.medzell.net/main-categories-application/therapeutic-devices/ | I88: exports@careonhealthcare.com | L88: Stated | N88: BV, TUV | O88: https://www.medzell.net/company/careon-healthcare-solutions-pvt-ltd/ | Q88: 10 | R88: =IF(Q88="","",IF(Q88>=60,"HIGH",IF(Q88>=30,"MEDIUM","LOW"))) | S88: New | T88: 2026-03-05 | U88: Seed=Medzell; Seed-file: output/medzell_company_urls.txt
A89: 88 | B89: High-Quality Medical Equipment Manufacturer | Carevel Medical Systems | D89: Manufacturer | E89: PPE | F89: Wound Care, Lab Consumables, Syringes & Needles, IV Infusion Sets, Gauze & Bandages, Disinfectants, IV Cannulas, Catheters | H89: https://www.medzell.net/main-categories-application/therapeutic-devices/ | I89: mukesh@carevelglobal.com | L89: Stated | N89: GMP, TUV | O89: https://www.medzell.net/company/carevel-medical-systems-pvt-ltd/ | Q89: 10 | R89: =IF(Q89="","",IF(Q89>=60,"HIGH",IF(Q89>=30,"MEDIUM","LOW"))) | S89: New | T89: 2026-03-05 | U89: Seed=Medzell; Seed-file: output/medzell_company_urls.txt
A90: 89 | B90: Cerajivan Healthtech - Advanced Colon Hydrotherapy Machines for Effective Detox and Better Health | D90: Manufacturer | E90: PPE | F90: Wound Care, Lab Consumables, Syringes & Needles, IV Infusion Sets, Gauze & Bandages, Disinfectants, IV Cannulas, Catheters | H90: https://www.medzell.net/main-categories-application/therapeutic-devices/ | I90: cerajivan@gmail.com | N90: TUV | O90: https://www.medzell.net/company/cerajivan-healthtech/ | Q90: 45 | R90: =IF(Q90="","",IF(Q90>=60,"HIGH",IF(Q90>=30,"MEDIUM","LOW"))) | S90: New | T90: 2026-03-05 | U90: Seed=Medzell; Seed-file: output/medzell_company_urls.txt
A91: 90 | B91: Quality and Excellence: The Cornerstones of a 40-Year Legacy in Hospital Supplies | D91: Manufacturer | E91: PPE | F91: Wound Care, Lab Consumables, Syringes & Needles, IV Infusion Sets, Gauze & Bandages, Disinfectants, IV Cannulas, Catheters | H91: https://www.medzell.net/main-categories-application/therapeutic-devices/ | I91: chatterjeesurgical@gmail.com | N91: TUV | O91: https://www.medzell.net/company/chatterjee-surgical/ | Q91: 45 | R91: =IF(Q91="","",IF(Q91>=60,"HIGH",IF(Q91>=30,"MEDIUM","LOW"))) | S91: New | T91: 2026-03-05 | U91: Seed=Medzell; Seed-file: output/medzell_company_urls.txt
A92: 91 | B92: Chengdu Fulcare Co., Ltd : Leading Manufacturer of Infection Control, Wound Care, Respiratory Health, and RFID Solutions. | D92: Manufacturer | E92: PPE | F92: Wound Care, Lab Consumables, Syringes & Needles, IV Infusion Sets, Gauze & Bandages, Disinfectants, IV Cannulas, Catheters | H92: https://www.medzell.net/main-categories-application/therapeutic-devices/ | I92: tom.zhao@fulcare.cn | L92: Stated | N92: TUV | O92: https://www.medzell.net/company/chengdu-fulcare-coltd/ | Q92: 10 | R92: =IF(Q92="","",IF(Q92>=60,"HIGH",IF(Q92>=30,"MEDIUM","LOW"))) | S92: New | T92: 2026-03-05 | U92: Seed=Medzell; Seed-file: output/medzell_company_urls.txt
A93: 92 | B93: Premium Supplier of Medical Disposables and Wound Care Products | D93: Manufacturer | E93: PPE | F93: Wound Care, Lab Consumables, Syringes & Needles, IV Infusion Sets, Gauze & Bandages, Disinfectants, IV Cannulas, Catheters | H93: https://www.medzell.net/main-categories-application/therapeutic-devices/ | I93: w118@csd.com.tw | L93: Stated | N93: FDA, GMP, TUV | O93: https://www.medzell.net/company/china-surgical-dressings-center-co-ltd-csd-taiwan/ | Q93: 10 | R93: =IF(Q93="","",IF(Q93>=60,"HIGH",IF(Q93>=30,"MEDIUM","LOW"))) | S93: New | T93: 2026-03-05 | U93: Seed=Medzell; Seed-file: output/medzell_company_urls.txt
A94: 93 | B94: Chiru Dental Equipments Kerala: Leading Supplier and Exporter of Hospital Furniture and Dental Chairs in India | D94: Manufacturer | E94: PPE | F94: Wound Care, Lab Consumables, Syringes & Needles, IV Infusion Sets, Gauze & Bandages, Disinfectants, IV Cannulas, Catheters | H94: https://www.medzell.net/main-categories-application/therapeutic-devices/ | I94: chirudentalkerala@gmail.com | N94: TUV | O94: https://www.medzell.net/company/chiru-dental-equipments-kerala/ | Q94: 45 | R94: =IF(Q94="","",IF(Q94>=60,"HIGH",IF(Q94>=30,"MEDIUM","LOW"))) | S94: New | T94: 2026-03-05 | U94: Seed=Medzell; Seed-file: output/medzell_company_urls.txt
A95: 94 | B95: Chromadent Dental Equipments: Trusted Manufacturer of High-Quality Dental Equipment | D95: Manufacturer | E95: PPE | F95: Wound Care, Lab Consumables, Syringes & Needles, IV Infusion Sets, Gauze & Bandages, Disinfectants, IV Cannulas, Catheters | H95: https://www.medzell.net/main-categories-application/therapeutic-devices/ | I95: info@chromadent.com | N95: TUV | O95: https://www.medzell.net/company/chromadent-dental-equipment/ | Q95: 25 | R95: =IF(Q95="","",IF(Q95>=60,"HIGH",IF(Q95>=30,"MEDIUM","LOW"))) | S95: New | T95: 2026-03-05 | U95: Seed=Medzell; Seed-file: output/medzell_company_urls.txt
A96: 95 | B96: Cistron Systems Pvt. Ltd. - High-Quality Medical Equipment Manufacturer for Healthcare Needs | D96: Manufacturer | E96: PPE | F96: Wound Care, Lab Consumables, Syringes & Needles, IV Infusion Sets, Gauze & Bandages, Disinfectants, IV Cannulas, Catheters | H96: https://www.medzell.net/main-categories-application/therapeutic-devices/ | I96: murali@cistronsystems.com | L96: Stated | N96: TUV | O96: https://www.medzell.net/company/cistron-systems-private-limited/ | Q96: 10 | R96: =IF(Q96="","",IF(Q96>=60,"HIGH",IF(Q96>=30,"MEDIUM","LOW"))) | S96: New | T96: 2026-03-05 | U96: Seed=Medzell; Seed-file: output/medzell_company_urls.txt
A97: 96 | B97: Advanced Obstetrics, Gynecology & Urology Solutions - Simurg Medical Enterprise | D97: Manufacturer | E97: PPE | F97: Wound Care, Lab Consumables, Syringes & Needles, IV Infusion Sets, Catheters, Gauze & Bandages, Disinfectants, IV Cannulas | H97: https://www.medzell.net/main-categories-application/therapeutic-devices/ | I97: nms@simurg.by | N97: TUV | O97: https://www.medzell.net/company/cjsc-simurg-medical-enterprise/ | Q97: 25 | R97: =IF(Q97="","",IF(Q97>=60,"HIGH",IF(Q97>=30,"MEDIUM","LOW"))) | S97: New | T97: 2026-03-05 | U97: Seed=Medzell; Seed-file: output/medzell_company_urls.txt
A98: 97 | B98: Leading Manufacturer of Medical Gadgets and Solutions - Clarity Medical Pvt. Ltd. | D98: Manufacturer | E98: PPE | F98: Wound Care, Lab Consumables, Syringes & Needles, IV Infusion Sets, Catheters, Gauze & Bandages, Disinfectants, IV Cannulas | H98: https://www.medzell.net/main-categories-application/therapeutic-devices/ | I98: sahib.bhatia@clarity-medical.com | M98: Stated | N98: FDA, TUV | O98: https://www.medzell.net/company/clarity-medical/ | Q98: 15 | R98: =IF(Q98="","",IF(Q98>=60,"HIGH",IF(Q98>=30,"MEDIUM","LOW"))) | S98: New | T98: 2026-03-05 | U98: Seed=Medzell; Seed-file: output/medzell_company_urls.txt
A99: 98 | B99: Leading Manufacturer of DVT Pumps, Air Mattresses, and More - Codex Solutions | D99: Manufacturer | E99: PPE | F99: Wound Care, Lab Consumables, Syringes & Needles, IV Infusion Sets, Gauze & Bandages, Disinfectants, IV Cannulas, Catheters | H99: https://www.medzell.net/main-categories-application/therapeutic-devices/ | I99: kedar@codexgpo.com | L99: Stated | M99: Stated | N99: TUV | O99: https://www.medzell.net/company/codex-solutions/ | Q99: 0 | R99: =IF(Q99="","",IF(Q99>=60,"HIGH",IF(Q99>=30,"MEDIUM","LOW"))) | S99: New | T99: 2026-03-05 | U99: Seed=Medzell; Seed-file: output/medzell_company_urls.txt
A100: 99 | B100: Cutting-Edge Neurocognitive Equipment for Diagnosis and Therapy | COEXIN Technologies Healthcare | D100: Manufacturer | E100: PPE | F100: Wound Care, Lab Consumables, Syringes & Needles, IV Infusion Sets, Catheters, Gauze & Bandages, Disinfectants, IV Cannulas | H100: https://www.medzell.net/main-categories-application/therapeutic-devices/ | I100: arshadkoya@gmail.com | L100: Stated | N100: TUV | O100: https://www.medzell.net/company/coexin-technologies-healthcare-private-limited/ | Q100: 30 | R100: =IF(Q100="","",IF(Q100>=60,"HIGH",IF(Q100>=30,"MEDIUM","LOW"))) | S100: New | T100: 2026-03-05 | U100: Seed=Medzell; Seed-file: output/medzell_company_urls.txt
...

Sheet Seed_URLs
A1: Seed URLs (Fix A) — paste directory/company pages here (500+). Scraper will extract emails + map categories and fill Supplier_Intelligence up to 180.
A2: Source_Name | B2: Country | C2: URL | D2: Category_Hint | E2: Notes | F2: Use (TRUE/FALSE)
A3: Medzell | C3: https://www.medzell.net/sitemap.xml | E3: seed sitemap | F3: TRUE
A4: Turkey_TurkishHealthcare | B4: Turkey | C4: https://turkishhealthcare.org/companies | E4: directory start | F4: TRUE
A5: Malaysia_MMDA | B5: Malaysia | C5: https://mmda.org.my/mmda-members-list/ | E5: directory start | F5: TRUE
A6: China_CAMDI | B6: China | C6: https://en.camdi.cn/member/index | E6: directory start | F6: TRUE
A7: France_SNITEM | B7: France | C7: https://www.snitem.fr/adherer/entreprises-adherentes/ | E7: directory start | F7: TRUE
A8: Italy_ConfindustriaDM | B8: Italy | C8: https://www.confindustriadm.it/le-aziende/ | E8: directory start | F8: TRUE
A9: Spain_FENIN | B9: Spain | C9: https://fenin.es/socios/ | E9: directory start | F9: TRUE
A10: UK_ABHI | B10: United Kingdom | C10: https://www.abhi.org.uk/membership/member-search/ | E10: directory start | F10: TRUE
A11: Germany_SPECTARIS | B11: Germany | C11: https://www.spectaris.de/verband/mitglieder | E11: directory start | F11: TRUE
A12: Egypt_CCI | B12: Egypt | C12: https://cci-egypt.org/membership/members-profiles/all-cci-members | E12: directory start | F12: TRUE

Sheet Source_Config
A1: Source_Name | B1: Base_URL | C1: Strategy | D1: Max_Items | E1: Max_Pages | F1: Delay_Seconds | G1: Notes
A2: Medzell | B2: https://www.medzell.net/ | C2: sitemap_company_pages | D2: 3000 | E2: 0 | F2: 0.5 | G2: Malaysia glove manufacturers; high yield
A3: Turkey_TurkishHealthcare | B3: https://turkishhealthcare.org/companies | C3: directory | D3: 3000 | E3: 200 | F3: 0.8 | G3: Turkey manufacturers/exporters; moderate yield
A4: Malaysia_MMDA | B4: https://mmda.org.my/mmda-members-list/ | C4: directory | D4: 3000 | E4: 0 | F4: 0.8 | G4: Add Medzell company URLs into Seed_URLs
A5: China_CAMDI | B5: https://en.camdi.cn/member/index | C5: directory_paginated | D5: 3000 | E5: 50 | F5: 1 | G5: Paste exhibitor profile URLs into Seed_URLs
A6: France_SNITEM | B6: https://www.snitem.fr/adherer/entreprises-adherentes/ | C6: directory | D6: 3000 | E6: 0 | F6: 1 | G6: Paste exhibitor profile URLs into Seed_URLs
A7: Italy_ConfindustriaDM | B7: https://www.confindustriadm.it/le-aziende/ | C7: directory | D7: 3000 | E7: 0 | F7: 1
A8: Spain_FENIN | B8: https://fenin.es/socios/ | C8: directory | D8: 3000 | E8: 80 | F8: 1
A9: UK_ABHI | B9: https://www.abhi.org.uk/membership/member-search/ | C9: directory | D9: 3000 | E9: 80 | F9: 1
A10: Germany_SPECTARIS | B10: https://www.spectaris.de/verband/mitglieder | C10: directory | D10: 3000 | E10: 0 | F10: 1
A11: Egypt_CCI | B11: https://cci-egypt.org/membership/members-profiles/all-cci-members | C11: directory_paginated | D11: 3000 | E11: 100 | F11: 1.2

Sheet Category_Keywords
A1: Category | B1: Keywords (comma-separated) | C1: Notes
A2: Wound Care | B2: dressing, bandage, foam dressing, hydrocolloid, silicone dressing, wound, plaster
A3: Syringes & Needles | B3: syringe, needle, hypodermic, luer lock, luer slip, insulin syringe, scalp vein
A4: IV Cannulas | B4: iv cannula, cannula, venflon, iv catheter
A5: IV Infusion Sets | B5: infusion set, iv set, drip set, transfusion set, burette
A6: Catheters | B6: foley, catheter, suction catheter, nelaton, urinary catheter, urology
A7: Gloves | B7: nitrile glove, latex glove, vinyl glove, examination glove, surgical glove
A8: PPE | B8: mask, respirator, gown, coverall, face shield, cap, shoe cover
A9: Gauze & Bandages | B9: gauze, gauze roll, gauze swab, bandage roll, crepe bandage, cotton
A10: Disinfectants | B10: alcohol swab, disinfectant, sanitizer, antiseptic, povidone, chlorhexidine
A11: Lab Consumables | B11: vacutainer, tube, pipette, specimen, lancet, sample cup, centrifuge tube

Sheet Benchmarks
A1: Category | B1: Benchmark Source | C1: How to use | D1: Link/Reference
A2: All categories | B2: UNICEF Supply Catalogue | C2: Sanity-check quote ranges; not landed cost | D2: https://supply.unicef.org/all-materials/medical-renewable.html?cat=2871&p=2&product_attributes=10
A3: Gloves (example) | B3: UNICEF product page | C3: Sanity-check specs & pricing display | D3: https://supply.unicef.org/s0330126.html

Sheet Risk_Model
A1: Factor | B1: Rule | C1: Points Added | D1: Rationale
A2: Email quality | B2: Free email domain (gmail/yahoo) OR no company-domain email | C2: 20 | D2: Higher fraud/low-traceability risk
A3: ISO 13485 | B3: Not explicitly stated (or no evidence link) | C3: 15 | D3: Strong quality signal for medical devices
A4: CE | B4: Not explicitly stated (or no evidence link) | C4: 10 | D4: Useful conformity signal (where applicable)
A5: Evidence URL | B5: Missing evidence link for email/cert claims | C5: 15 | D5: Cannot verify quickly
A6: Export experience | B6: No explicit export markets/clients stated | C6: 10 | D6: Unknown export handling maturity
A7: Supplier type | B7: Exporter without manufacturer disclosure | C7: 10 | D7: Need factory validation

Sheet Run_Log
A1: Run_Timestamp | B1: Rows_Filled | C1: Sources_Used | D1: Notes
A2: 2026-03-04T20:40:09.227035Z | D2: Workbook generated. Run scraper in Codespaces to populate Supplier_Intelligence.
A3: 2026-03-05T00:21:02.419940+00:00 | B3: 0 | C3: MULTI|Malaysia|append | D3: Visited 1 seeds; wrote 0 NEW suppliers. limit=300 delay=0.8s
A4: 2026-03-05T00:21:06.145195+00:00 | B4: 0 | C4: MULTI|Turkey|append | D4: Visited 1 seeds; wrote 0 NEW suppliers. limit=300 delay=0.8s
A5: 2026-03-05T00:21:10.167447+00:00 | B5: 0 | C5: MULTI|China|append | D5: Visited 1 seeds; wrote 0 NEW suppliers. limit=300 delay=0.8s
A6: 2026-03-05T00:43:16.908770+00:00 | B6: 441 | C6: Medzell|ALL|append | D6: Visited 629 seeds; wrote 441 NEW suppliers. limit=600 delay=0.5s

Sheet Outreach_Batch
A1: Outreach Batch Builder (filters + export-ready list)
J2: Categories | K2: Countries | L2: RiskLevels
A3: Primary Category | D3: Filtered suppliers (Excel 365 dynamic formula). If your Excel doesn't support this, use the Python exporter script. | J3: Wound Care | K3: Malaysia | L3: LOW
A4: Country | D4: Company | E4: Email(s) | F4: Country | G4: Risk_Level | H4: Evidence_URL | J4: Syringes & Needles | K4: Turkey | L4: MED
A5: Max Risk Level | B5: MED | J5: IV Cannulas | K5: China | L5: HIGH
A6: Batch Size | B6: 100 | D6: =LET(cat,$B$3,cty,$B$4,maxRisk,$B$5,batchSize,$B$6,batchNum,$B$7,tbl,Supplier_Intelligence!$A$2:$U$3001,companies,INDEX(tbl,,2),emails,INDEX(tbl,,9),country,INDEX(tbl,,3),risk,INDEX(tbl,,18),evidence,INDEX(tbl,,15),isRisk,IF(maxRisk="LOW",risk="LOW",IF(maxRisk="MED",(risk="LOW")+(risk="MED"),1)),isCat,IF(cat="",1,INDEX(tbl,,5)=cat),isCty,IF(cty="",1,country=cty),mask,(companies<>"")*isRisk*isCat*isCty*(emails<>""),filtered,FILTER(HSTACK(companies,emails,country,risk,evidence),mask,""),start,(batchNum-1)*batchSize+1,TAKE(DROP(filtered,start-1),batchSize)) | J6: IV Infusion Sets | K6: India
A7: Batch # (1,2,3...) | B7: 1 | J7: Catheters | K7: Egypt
D8: =D6 | J8: Gloves | K8: Jordan
J9: PPE | K9: United Arab Emirates
J10: Gauze & Bandages | K10: Saudi Arabia
J11: Disinfectants | K11: Qatar
J12: Lab Consumables | K12: Kuwait
K13: Oman
K14: Bahrain
K15: Lebanon
K16: Iraq
K17: Yemen
K18: Palestine
K19: Germany
K20: France
K21: Italy
K22: Spain
K23: United Kingdom
K24: Syria

Sheet View_Malaysia
A1: View: Malaysia (filter by category + risk)
J2: Categories | K2: RiskLevels
A3: Category (optional) | D3: Filtered suppliers | J3: Wound Care | K3: LOW
A4: Max Risk (LOW/MED/HIGH) | B4: MED | D4: Supplier_ID | E4: Company | F4: Country | G4: Supplier_Type | H4: Primary_Category | I4: Secondary_Categories | J4: Syringes & Needles | K4: MED | L4: Risk_Level | M4: Evidence_URL
D5: =LET(cty,"Malaysia",cat,$B$3,maxRisk,$B$4,tbl,Supplier_Intelligence!$A$2:$U$3001,sid,INDEX(tbl,,1),co,INDEX(tbl,,2),country,INDEX(tbl,,3),stype,INDEX(tbl,,4),pcat,INDEX(tbl,,5),scat,INDEX(tbl,,6),web,INDEX(tbl,,8),em,INDEX(tbl,,9),risk,INDEX(tbl,,18),ev,INDEX(tbl,,15),isCty,country=cty,isCat,IF(cat="",1,pcat=cat),isRisk,IF(maxRisk="LOW",risk="LOW",IF(maxRisk="MED",(risk="LOW")+(risk="MED"),1)),mask,(co<>"")*(em<>"")*isCty*isCat*isRisk,FILTER(HSTACK(sid,co,country,stype,pcat,scat,web,em,risk,ev),mask,"")) | J5: IV Cannulas | K5: HIGH
J6: IV Infusion Sets
J7: Catheters
J8: Gloves
J9: PPE
J10: Gauze & Bandages
J11: Disinfectants
J12: Lab Consumables

Sheet View_Turkey
A1: View: Turkey (filter by category + risk)
J2: Categories | K2: RiskLevels
A3: Category (optional) | D3: Filtered suppliers | J3: Wound Care | K3: LOW
A4: Max Risk (LOW/MED/HIGH) | B4: MED | D4: Supplier_ID | E4: Company | F4: Country | G4: Supplier_Type | H4: Primary_Category | I4: Secondary_Categories | J4: Syringes & Needles | K4: MED | L4: Risk_Level | M4: Evidence_URL
D5: =LET(cty,"Turkey",cat,$B$3,maxRisk,$B$4,tbl,Supplier_Intelligence!$A$2:$U$3001,sid,INDEX(tbl,,1),co,INDEX(tbl,,2),country,INDEX(tbl,,3),stype,INDEX(tbl,,4),pcat,INDEX(tbl,,5),scat,INDEX(tbl,,6),web,INDEX(tbl,,8),em,INDEX(tbl,,9),risk,INDEX(tbl,,18),ev,INDEX(tbl,,15),isCty,country=cty,isCat,IF(cat="",1,pcat=cat),isRisk,IF(maxRisk="LOW",risk="LOW",IF(maxRisk="MED",(risk="LOW")+(risk="MED"),1)),mask,(co<>"")*(em<>"")*isCty*isCat*isRisk,FILTER(HSTACK(sid,co,country,stype,pcat,scat,web,em,risk,ev),mask,"")) | J5: IV Cannulas | K5: HIGH
J6: IV Infusion Sets
J7: Catheters
J8: Gloves
J9: PPE
J10: Gauze & Bandages
J11: Disinfectants
J12: Lab Consumables

Sheet View_China
A1: View: China (filter by category + risk)
J2: Categories | K2: RiskLevels
A3: Category (optional) | D3: Filtered suppliers | J3: Wound Care | K3: LOW
A4: Max Risk (LOW/MED/HIGH) | B4: MED | D4: Supplier_ID | E4: Company | F4: Country | G4: Supplier_Type | H4: Primary_Category | I4: Secondary_Categories | J4: Syringes & Needles | K4: MED | L4: Risk_Level | M4: Evidence_URL
D5: =LET(cty,"China",cat,$B$3,maxRisk,$B$4,tbl,Supplier_Intelligence!$A$2:$U$3001,sid,INDEX(tbl,,1),co,INDEX(tbl,,2),country,INDEX(tbl,,3),stype,INDEX(tbl,,4),pcat,INDEX(tbl,,5),scat,INDEX(tbl,,6),web,INDEX(tbl,,8),em,INDEX(tbl,,9),risk,INDEX(tbl,,18),ev,INDEX(tbl,,15),isCty,country=cty,isCat,IF(cat="",1,pcat=cat),isRisk,IF(maxRisk="LOW",risk="LOW",IF(maxRisk="MED",(risk="LOW")+(risk="MED"),1)),mask,(co<>"")*(em<>"")*isCty*isCat*isRisk,FILTER(HSTACK(sid,co,country,stype,pcat,scat,web,em,risk,ev),mask,"")) | J5: IV Cannulas | K5: HIGH
J6: IV Infusion Sets
J7: Catheters
J8: Gloves
J9: PPE
J10: Gauze & Bandages
J11: Disinfectants
J12: Lab Consumables

Sheet View_Egypt
A1: View: Egypt (filter by category + risk)
J2: Categories | K2: RiskLevels
A3: Category (optional) | D3: Filtered suppliers | J3: Wound Care | K3: LOW
A4: Max Risk (LOW/MED/HIGH) | B4: MED | D4: Supplier_ID | E4: Company | F4: Country | G4: Supplier_Type | H4: Primary_Category | I4: Secondary_Categories | J4: Syringes & Needles | K4: MED | L4: Risk_Level | M4: Evidence_URL
D5: =LET(cty,"Egypt",cat,$B$3,maxRisk,$B$4,tbl,Supplier_Intelligence!$A$2:$U$3001,sid,INDEX(tbl,,1),co,INDEX(tbl,,2),country,INDEX(tbl,,3),stype,INDEX(tbl,,4),pcat,INDEX(tbl,,5),scat,INDEX(tbl,,6),web,INDEX(tbl,,8),em,INDEX(tbl,,9),risk,INDEX(tbl,,18),ev,INDEX(tbl,,15),isCty,country=cty,isCat,IF(cat="",1,pcat=cat),isRisk,IF(maxRisk="LOW",risk="LOW",IF(maxRisk="MED",(risk="LOW")+(risk="MED"),1)),mask,(co<>"")*(em<>"")*isCty*isCat*isRisk,FILTER(HSTACK(sid,co,country,stype,pcat,scat,web,em,risk,ev),mask,"")) | J5: IV Cannulas | K5: HIGH
J6: IV Infusion Sets
J7: Catheters
J8: Gloves
J9: PPE
J10: Gauze & Bandages
J11: Disinfectants
J12: Lab Consumables

Sheet View_Germany
A1: View: Germany (filter by category + risk)
J2: Categories | K2: RiskLevels
A3: Category (optional) | D3: Filtered suppliers | J3: Wound Care | K3: LOW
A4: Max Risk (LOW/MED/HIGH) | B4: MED | D4: Supplier_ID | E4: Company | F4: Country | G4: Supplier_Type | H4: Primary_Category | I4: Secondary_Categories | J4: Syringes & Needles | K4: MED | L4: Risk_Level | M4: Evidence_URL
D5: =LET(cty,"Germany",cat,$B$3,maxRisk,$B$4,tbl,Supplier_Intelligence!$A$2:$U$3001,sid,INDEX(tbl,,1),co,INDEX(tbl,,2),country,INDEX(tbl,,3),stype,INDEX(tbl,,4),pcat,INDEX(tbl,,5),scat,INDEX(tbl,,6),web,INDEX(tbl,,8),em,INDEX(tbl,,9),risk,INDEX(tbl,,18),ev,INDEX(tbl,,15),isCty,country=cty,isCat,IF(cat="",1,pcat=cat),isRisk,IF(maxRisk="LOW",risk="LOW",IF(maxRisk="MED",(risk="LOW")+(risk="MED"),1)),mask,(co<>"")*(em<>"")*isCty*isCat*isRisk,FILTER(HSTACK(sid,co,country,stype,pcat,scat,web,em,risk,ev),mask,"")) | J5: IV Cannulas | K5: HIGH
J6: IV Infusion Sets
J7: Catheters
J8: Gloves
J9: PPE
J10: Gauze & Bandages
J11: Disinfectants
J12: Lab Consumables

Sheet View_France
A1: View: France (filter by category + risk)
J2: Categories | K2: RiskLevels
A3: Category (optional) | D3: Filtered suppliers | J3: Wound Care | K3: LOW
A4: Max Risk (LOW/MED/HIGH) | B4: MED | D4: Supplier_ID | E4: Company | F4: Country | G4: Supplier_Type | H4: Primary_Category | I4: Secondary_Categories | J4: Syringes & Needles | K4: MED | L4: Risk_Level | M4: Evidence_URL
D5: =LET(cty,"France",cat,$B$3,maxRisk,$B$4,tbl,Supplier_Intelligence!$A$2:$U$3001,sid,INDEX(tbl,,1),co,INDEX(tbl,,2),country,INDEX(tbl,,3),stype,INDEX(tbl,,4),pcat,INDEX(tbl,,5),scat,INDEX(tbl,,6),web,INDEX(tbl,,8),em,INDEX(tbl,,9),risk,INDEX(tbl,,18),ev,INDEX(tbl,,15),isCty,country=cty,isCat,IF(cat="",1,pcat=cat),isRisk,IF(maxRisk="LOW",risk="LOW",IF(maxRisk="MED",(risk="LOW")+(risk="MED"),1)),mask,(co<>"")*(em<>"")*isCty*isCat*isRisk,FILTER(HSTACK(sid,co,country,stype,pcat,scat,web,em,risk,ev),mask,"")) | J5: IV Cannulas | K5: HIGH
J6: IV Infusion Sets
J7: Catheters
J8: Gloves
J9: PPE
J10: Gauze & Bandages
J11: Disinfectants
J12: Lab Consumables

Sheet View_Italy
A1: View: Italy (filter by category + risk)
J2: Categories | K2: RiskLevels
A3: Category (optional) | D3: Filtered suppliers | J3: Wound Care | K3: LOW
A4: Max Risk (LOW/MED/HIGH) | B4: MED | D4: Supplier_ID | E4: Company | F4: Country | G4: Supplier_Type | H4: Primary_Category | I4: Secondary_Categories | J4: Syringes & Needles | K4: MED | L4: Risk_Level | M4: Evidence_URL
D5: =LET(cty,"Italy",cat,$B$3,maxRisk,$B$4,tbl,Supplier_Intelligence!$A$2:$U$3001,sid,INDEX(tbl,,1),co,INDEX(tbl,,2),country,INDEX(tbl,,3),stype,INDEX(tbl,,4),pcat,INDEX(tbl,,5),scat,INDEX(tbl,,6),web,INDEX(tbl,,8),em,INDEX(tbl,,9),risk,INDEX(tbl,,18),ev,INDEX(tbl,,15),isCty,country=cty,isCat,IF(cat="",1,pcat=cat),isRisk,IF(maxRisk="LOW",risk="LOW",IF(maxRisk="MED",(risk="LOW")+(risk="MED"),1)),mask,(co<>"")*(em<>"")*isCty*isCat*isRisk,FILTER(HSTACK(sid,co,country,stype,pcat,scat,web,em,risk,ev),mask,"")) | J5: IV Cannulas | K5: HIGH
J6: IV Infusion Sets
J7: Catheters
J8: Gloves
J9: PPE
J10: Gauze & Bandages
J11: Disinfectants
J12: Lab Consumables

Sheet View_Spain
A1: View: Spain (filter by category + risk)
J2: Categories | K2: RiskLevels
A3: Category (optional) | D3: Filtered suppliers | J3: Wound Care | K3: LOW
A4: Max Risk (LOW/MED/HIGH) | B4: MED | D4: Supplier_ID | E4: Company | F4: Country | G4: Supplier_Type | H4: Primary_Category | I4: Secondary_Categories | J4: Syringes & Needles | K4: MED | L4: Risk_Level | M4: Evidence_URL
D5: =LET(cty,"Spain",cat,$B$3,maxRisk,$B$4,tbl,Supplier_Intelligence!$A$2:$U$3001,sid,INDEX(tbl,,1),co,INDEX(tbl,,2),country,INDEX(tbl,,3),stype,INDEX(tbl,,4),pcat,INDEX(tbl,,5),scat,INDEX(tbl,,6),web,INDEX(tbl,,8),em,INDEX(tbl,,9),risk,INDEX(tbl,,18),ev,INDEX(tbl,,15),isCty,country=cty,isCat,IF(cat="",1,pcat=cat),isRisk,IF(maxRisk="LOW",risk="LOW",IF(maxRisk="MED",(risk="LOW")+(risk="MED"),1)),mask,(co<>"")*(em<>"")*isCty*isCat*isRisk,FILTER(HSTACK(sid,co,country,stype,pcat,scat,web,em,risk,ev),mask,"")) | J5: IV Cannulas | K5: HIGH
J6: IV Infusion Sets
J7: Catheters
J8: Gloves
J9: PPE
J10: Gauze & Bandages
J11: Disinfectants
J12: Lab Consumables

Sheet View_United_Kingdom
A1: View: United Kingdom (filter by category + risk)
J2: Categories | K2: RiskLevels
A3: Category (optional) | D3: Filtered suppliers | J3: Wound Care | K3: LOW
A4: Max Risk (LOW/MED/HIGH) | B4: MED | D4: Supplier_ID | E4: Company | F4: Country | G4: Supplier_Type | H4: Primary_Category | I4: Secondary_Categories | J4: Syringes & Needles | K4: MED | L4: Risk_Level | M4: Evidence_URL
D5: =LET(cty,"United Kingdom",cat,$B$3,maxRisk,$B$4,tbl,Supplier_Intelligence!$A$2:$U$3001,sid,INDEX(tbl,,1),co,INDEX(tbl,,2),country,INDEX(tbl,,3),stype,INDEX(tbl,,4),pcat,INDEX(tbl,,5),scat,INDEX(tbl,,6),web,INDEX(tbl,,8),em,INDEX(tbl,,9),risk,INDEX(tbl,,18),ev,INDEX(tbl,,15),isCty,country=cty,isCat,IF(cat="",1,pcat=cat),isRisk,IF(maxRisk="LOW",risk="LOW",IF(maxRisk="MED",(risk="LOW")+(risk="MED"),1)),mask,(co<>"")*(em<>"")*isCty*isCat*isRisk,FILTER(HSTACK(sid,co,country,stype,pcat,scat,web,em,risk,ev),mask,"")) | J5: IV Cannulas | K5: HIGH
J6: IV Infusion Sets
J7: Catheters
J8: Gloves
J9: PPE
J10: Gauze & Bandages
J11: Disinfectants
J12: Lab Consumables
